<proof id="dpc-ind-001640-nl-sen.p.10.s.1_1.xml" date="27052020">
 <string>een week voor de eerste vlucht van een spaceshuttle sinds de Columbiamissie van 2003 gepland staat kreeg de NASA rapporten binnen over een doelbewust gesaboteerde computer een op het nippertje ontdekt lek in de cabine dat ijlings hersteld moet worden en een niet-werkende thermostaat die de hydraulische systemen van de shuttle zou moeten controleren</string>
 <lexicon>
  <lexicon_item id="1"><word>een</word><pos1>det</pos1><pos2>LID(onbep,stan,agr)</pos2><lemma>een</lemma><formula><box dep="det"><impl><atom id="5">n</atom><box dep="mod"><impl><box dep="mod"><impl><atom id="1">smain</atom><atom id="8">smain</atom></impl></box><box dep="mod"><impl><atom id="37">smain</atom><atom id="4">smain</atom></impl></box></impl></box></impl></box></formula></lexicon_item>
  <lexicon_item id="2"><word>week</word><pos1>noun</pos1><pos2>N(soort,ev,basis,zijd,stan)</pos2><lemma>week</lemma><formula><atom id="5">n</atom></formula></lexicon_item>
  <lexicon_item id="3"><word>voor</word><pos1>comp</pos1><pos2>VZ(init)</pos2><lemma>voor</lemma><formula><impl><dia dep="cmp_body"><atom id="33">ssub</atom></dia><box dep="mod"><impl><atom id="1">smain</atom><atom id="8">smain</atom></impl></box></impl></formula></lexicon_item>
  <lexicon_item id="4"><word>de</word><pos1>det</pos1><pos2>LID(bep,stan,rest)</pos2><lemma>de</lemma><formula><box dep="det"><impl><atom id="13">n</atom><atom id="10">np</atom></impl></box></formula></lexicon_item>
  <lexicon_item id="5"><word>eerste</word><pos1>num</pos1><pos2>TW(rang,prenom,stan)</pos2><lemma>één</lemma><formula><box dep="mod"><impl><atom id="10">np</atom><atom id="12">np</atom></impl></box></formula></lexicon_item>
  <lexicon_item id="6"><word>vlucht</word><pos1>noun</pos1><pos2>N(soort,ev,basis,zijd,stan)</pos2><lemma>vlucht</lemma><formula><atom id="13">n</atom></formula></lexicon_item>
  <lexicon_item id="7"><word>van</word><pos1>prep</pos1><pos2>VZ(init)</pos2><lemma>van</lemma><formula><impl><dia dep="obj1"><atom id="18">np</atom></dia><box dep="mod"><impl><atom id="12">np</atom><atom id="16">np</atom></impl></box></impl></formula></lexicon_item>
  <lexicon_item id="8"><word>een</word><pos1>det</pos1><pos2>LID(onbep,stan,agr)</pos2><lemma>een</lemma><formula><box dep="det"><impl><atom id="19">n</atom><atom id="18">np</atom></impl></box></formula></lexicon_item>
  <lexicon_item id="9"><word>spaceshuttle</word><pos1>noun</pos1><pos2>N(soort,ev,basis,zijd,stan)</pos2><lemma>spaceshuttle</lemma><formula><atom id="19">n</atom></formula></lexicon_item>
  <lexicon_item id="10"><word>sinds</word><pos1>prep</pos1><pos2>VZ(init)</pos2><lemma>sinds</lemma><formula><impl><dia dep="obj1"><atom id="28">np</atom></dia><box dep="mod"><impl><atom id="16">np</atom><atom id="22">np</atom></impl></box></impl></formula></lexicon_item>
  <lexicon_item id="11"><word>de</word><pos1>det</pos1><pos2>LID(bep,stan,rest)</pos2><lemma>de</lemma><formula><box dep="det"><impl><atom id="25">n</atom><atom id="24">np</atom></impl></box></formula></lexicon_item>
  <lexicon_item id="12"><word>Columbiamissie</word><pos1>noun</pos1><pos2>N(soort,ev,basis,zijd,stan)</pos2><lemma>Columbiamissie</lemma><formula><atom id="25">n</atom></formula></lexicon_item>
  <lexicon_item id="13"><word>van</word><pos1>prep</pos1><pos2>VZ(init)</pos2><lemma>van</lemma><formula><impl><dia dep="obj1"><atom id="29">tw</atom></dia><box dep="mod"><impl><atom id="24">np</atom><atom id="28">np</atom></impl></box></impl></formula></lexicon_item>
  <lexicon_item id="14"><word>2003</word><pos1>noun</pos1><pos2>TW(hoofd,vrij)</pos2><lemma>2003</lemma><formula><atom id="29">tw</atom></formula></lexicon_item>
  <lexicon_item id="15"><word>gepland</word><pos1>verb</pos1><pos2>WW(vd,vrij,zonder)</pos2><lemma>plannen</lemma><formula><atom id="30">ww</atom></formula></lexicon_item>
  <lexicon_item id="16"><word>staat</word><pos1>verb</pos1><pos2>WW(pv,tgw,met-t)</pos2><lemma>staan</lemma><formula><impl><dia dep="vc"><atom id="30">ww</atom></dia><impl><dia dep="su"><atom id="22">np</atom></dia><atom id="33">ssub</atom></impl></impl></formula></lexicon_item>
  <lexicon_item id="17"><word>kreeg</word><pos1>verb</pos1><pos2>WW(pv,verl,ev)</pos2><lemma>krijgen</lemma><formula><impl><dia dep="svp"><atom id="42">vz</atom></dia><impl><dia dep="obj1"><atom id="45">np</atom></dia><impl><dia dep="su"><atom id="39">np</atom></dia><atom id="37">smain</atom></impl></impl></impl></formula></lexicon_item>
  <lexicon_item id="18"><word>de</word><pos1>det</pos1><pos2>LID(bep,stan,rest)</pos2><lemma>de</lemma><formula><box dep="det"><impl><atom id="40">n</atom><atom id="39">np</atom></impl></box></formula></lexicon_item>
  <lexicon_item id="19"><word>NASA</word><pos1>name</pos1><pos2>N(eigen,ev,basis,zijd,stan)</pos2><lemma>NASA</lemma><formula><atom id="40">n</atom></formula></lexicon_item>
  <lexicon_item id="20"><word>rapporten</word><pos1>noun</pos1><pos2>N(soort,mv,basis)</pos2><lemma>rapport</lemma><formula><atom id="41">np</atom></formula></lexicon_item>
  <lexicon_item id="21"><word>binnen</word><pos1>part</pos1><pos2>VZ(fin)</pos2><lemma>binnen</lemma><formula><atom id="42">vz</atom></formula></lexicon_item>
  <lexicon_item id="22"><word>over</word><pos1>prep</pos1><pos2>VZ(init)</pos2><lemma>over</lemma><formula><impl><dia dep="obj1"><atom id="89">np</atom></dia><box dep="mod"><impl><atom id="41">np</atom><atom id="45">np</atom></impl></box></impl></formula></lexicon_item>
  <lexicon_item id="23"><word>een</word><pos1>det</pos1><pos2>LID(onbep,stan,agr)</pos2><lemma>een</lemma><formula><box dep="det"><impl><atom id="54">n</atom><atom id="47">np</atom></impl></box></formula></lexicon_item>
  <lexicon_item id="24"><word>doelbewust</word><pos1>adj</pos1><pos2>ADJ(vrij,basis,zonder)</pos2><lemma>doelbewust</lemma><formula><box dep="mod"><impl><box dep="mod"><impl><atom id="48">np</atom><atom id="53">np</atom></impl></box><box dep="mod"><impl><atom id="47">np</atom><atom id="51">np</atom></impl></box></impl></box></formula></lexicon_item>
  <lexicon_item id="25"><word>gesaboteerde</word><pos1>adj</pos1><pos2>WW(vd,prenom,met-e)</pos2><lemma>saboteren</lemma><formula><box dep="mod"><impl><atom id="48">np</atom><atom id="53">np</atom></impl></box></formula></lexicon_item>
  <lexicon_item id="26"><word>computer</word><pos1>noun</pos1><pos2>N(soort,ev,basis,zijd,stan)</pos2><lemma>computer</lemma><formula><atom id="54">n</atom></formula></lexicon_item>
  <lexicon_item id="27"><word>een</word><pos1>det</pos1><pos2>LID(onbep,stan,agr)</pos2><lemma>een</lemma><formula><box dep="det"><impl><atom id="67">adj</atom><atom id="56">np</atom></impl></box></formula></lexicon_item>
  <lexicon_item id="28"><word>op</word><pos1>prep</pos1><pos2>VZ(init)</pos2><lemma>op</lemma><formula><impl><dia dep="obj1"><atom id="63">np</atom></dia><box dep="mod"><impl><box dep="mod"><impl><atom id="58">np</atom><atom id="66">np</atom></impl></box><box dep="mod"><impl><atom id="56">np</atom><atom id="61">np</atom></impl></box></impl></box></impl></formula></lexicon_item>
  <lexicon_item id="29"><word>het</word><pos1>det</pos1><pos2>LID(bep,stan,evon)</pos2><lemma>het</lemma><formula><box dep="det"><impl><atom id="64">n</atom><atom id="63">np</atom></impl></box></formula></lexicon_item>
  <lexicon_item id="30"><word>nippertje</word><pos1>noun</pos1><pos2>N(soort,ev,dim,onz,stan)</pos2><lemma>nipper</lemma><formula><atom id="64">n</atom></formula></lexicon_item>
  <lexicon_item id="31"><word>ontdekt</word><pos1>adj</pos1><pos2>WW(vd,prenom,zonder)</pos2><lemma>ontdekken</lemma><formula><box dep="mod"><impl><atom id="58">np</atom><atom id="66">np</atom></impl></box></formula></lexicon_item>
  <lexicon_item id="32"><word>lek</word><pos1>noun</pos1><pos2>ADJ(vrij,basis,zonder)</pos2><lemma>lek</lemma><formula><atom id="67">adj</atom></formula></lexicon_item>
  <lexicon_item id="33"><word>in</word><pos1>prep</pos1><pos2>VZ(init)</pos2><lemma>in</lemma><formula><impl><dia dep="obj1"><atom id="72">np</atom></dia><box dep="mod"><impl><atom id="61">np</atom><atom id="70">np</atom></impl></box></impl></formula></lexicon_item>
  <lexicon_item id="34"><word>de</word><pos1>det</pos1><pos2>LID(bep,stan,rest)</pos2><lemma>de</lemma><formula><box dep="det"><impl><atom id="73">n</atom><atom id="72">np</atom></impl></box></formula></lexicon_item>
  <lexicon_item id="35"><word>cabine</word><pos1>noun</pos1><pos2>N(soort,ev,basis,zijd,stan)</pos2><lemma>cabine</lemma><formula><atom id="73">n</atom></formula></lexicon_item>
  <lexicon_item id="36"><word>dat</word><pos1>pron</pos1><pos2>VNW(betr,pron,stan,vol,3,ev)</pos2><lemma>dat</lemma><formula><impl><dia dep="rhd_body"><impl><dia dep="su"><atom id="74">vnw</atom></dia><atom id="83">ssub</atom></impl></dia><box dep="mod"><impl><atom id="70">np</atom><atom id="77">np</atom></impl></box></impl></formula></lexicon_item>
  <lexicon_item id="37"><word>ijlings</word><pos1>adv</pos1><pos2>ADJ(vrij,basis,zonder)</pos2><lemma>ijlings</lemma><formula><box dep="mod"><impl><atom id="80">ppart</atom><atom id="79">ppart</atom></impl></box></formula></lexicon_item>
  <lexicon_item id="38"><word>hersteld</word><pos1>verb</pos1><pos2>WW(vd,vrij,zonder)</pos2><lemma>herstellen</lemma><formula><atom id="80">ppart</atom></formula></lexicon_item>
  <lexicon_item id="39"><word>moet</word><pos1>verb</pos1><pos2>WW(pv,tgw,ev)</pos2><lemma>moeten</lemma><formula><impl><dia dep="vc"><atom id="85">inf</atom></dia><impl><dia dep="su"><atom id="74">vnw</atom></dia><atom id="83">ssub</atom></impl></impl></formula></lexicon_item>
  <lexicon_item id="40"><word>worden</word><pos1>verb</pos1><pos2>WW(inf,vrij,zonder)</pos2><lemma>worden</lemma><formula><impl><dia dep="vc"><atom id="79">ppart</atom></dia><atom id="85">inf</atom></impl></formula></lexicon_item>
  <lexicon_item id="41"><word>en</word><pos1>vg</pos1><pos2>VG(neven)</pos2><lemma>en</lemma><formula><impl><dia dep="cnj"><atom id="51">np</atom></dia><impl><dia dep="cnj"><atom id="77">np</atom></dia><impl><dia dep="cnj"><atom id="98">np</atom></dia><atom id="89">np</atom></impl></impl></impl></formula></lexicon_item>
  <lexicon_item id="42"><word>een</word><pos1>det</pos1><pos2>LID(onbep,stan,agr)</pos2><lemma>een</lemma><formula><box dep="det"><impl><atom id="94">n</atom><atom id="91">np</atom></impl></box></formula></lexicon_item>
  <lexicon_item id="43"><word>niet-werkende</word><pos1>adj</pos1><pos2>ADJ(prenom,basis,met-e,stan)</pos2><lemma>niet-werkend</lemma><formula><box dep="mod"><impl><atom id="91">np</atom><atom id="93">np</atom></impl></box></formula></lexicon_item>
  <lexicon_item id="44"><word>thermostaat</word><pos1>noun</pos1><pos2>N(soort,ev,basis,zijd,stan)</pos2><lemma>thermostaat</lemma><formula><atom id="94">n</atom></formula></lexicon_item>
  <lexicon_item id="45"><word>die</word><pos1>pron</pos1><pos2>VNW(betr,pron,stan,vol,persoon,getal)</pos2><lemma>die</lemma><formula><impl><dia dep="rhd_body"><impl><dia dep="su"><atom id="95">vnw</atom></dia><atom id="112">ssub</atom></impl></dia><box dep="mod"><impl><atom id="93">np</atom><atom id="98">np</atom></impl></box></impl></formula></lexicon_item>
  <lexicon_item id="46"><word>de</word><pos1>det</pos1><pos2>LID(bep,stan,rest)</pos2><lemma>de</lemma><formula><box dep="det"><impl><atom id="103">n</atom><atom id="100">np</atom></impl></box></formula></lexicon_item>
  <lexicon_item id="47"><word>hydraulische</word><pos1>adj</pos1><pos2>ADJ(prenom,basis,met-e,stan)</pos2><lemma>hydraulisch</lemma><formula><box dep="mod"><impl><atom id="100">np</atom><atom id="102">np</atom></impl></box></formula></lexicon_item>
  <lexicon_item id="48"><word>systemen</word><pos1>noun</pos1><pos2>N(soort,mv,basis)</pos2><lemma>systeem</lemma><formula><atom id="103">n</atom></formula></lexicon_item>
  <lexicon_item id="49"><word>van</word><pos1>prep</pos1><pos2>VZ(init)</pos2><lemma>van</lemma><formula><impl><dia dep="obj1"><atom id="108">np</atom></dia><box dep="mod"><impl><atom id="102">np</atom><atom id="106">np</atom></impl></box></impl></formula></lexicon_item>
  <lexicon_item id="50"><word>de</word><pos1>det</pos1><pos2>LID(bep,stan,rest)</pos2><lemma>de</lemma><formula><box dep="det"><impl><atom id="109">n</atom><atom id="108">np</atom></impl></box></formula></lexicon_item>
  <lexicon_item id="51"><word>shuttle</word><pos1>noun</pos1><pos2>N(soort,ev,basis,zijd,stan)</pos2><lemma>shuttle</lemma><formula><atom id="109">n</atom></formula></lexicon_item>
  <lexicon_item id="52"><word>zou</word><pos1>verb</pos1><pos2>WW(pv,verl,ev)</pos2><lemma>zullen</lemma><formula><impl><dia dep="vc"><atom id="114">inf</atom></dia><impl><dia dep="su"><atom id="95">vnw</atom></dia><atom id="112">ssub</atom></impl></impl></formula></lexicon_item>
  <lexicon_item id="53"><word>moeten</word><pos1>verb</pos1><pos2>WW(inf,vrij,zonder)</pos2><lemma>moeten</lemma><formula><impl><dia dep="vc"><atom id="116">inf</atom></dia><atom id="114">inf</atom></impl></formula></lexicon_item>
  <lexicon_item id="54"><word>controleren</word><pos1>verb</pos1><pos2>WW(inf,vrij,zonder)</pos2><lemma>controleren</lemma><formula><impl><dia dep="obj1"><atom id="106">np</atom></dia><atom id="116">inf</atom></impl></formula></lexicon_item>
 </lexicon>
<rule name="il"><antecedent><formula id="1"><atom id="5">n</atom></formula><formula id="2"><impl><atom id="5">n</atom><impl><impl><atom id="1">smain</atom><atom id="8">smain</atom></impl><impl><atom id="37">smain</atom><atom id="4">smain</atom></impl></impl></impl></formula><formula id="3"><atom id="30">ww</atom></formula><formula id="4"><impl><atom id="30">ww</atom><impl><atom id="22">np</atom><atom id="33">ssub</atom></impl></impl></formula><formula id="5"><atom id="29">tw</atom></formula><formula id="6"><impl><atom id="29">tw</atom><impl><atom id="24">np</atom><atom id="28">np</atom></impl></impl></formula><formula id="7"><atom id="25">n</atom></formula><formula id="8"><impl><atom id="25">n</atom><atom id="24">np</atom></impl></formula><formula id="9"><impl><atom id="28">np</atom><impl><atom id="16">np</atom><atom id="22">np</atom></impl></impl></formula><formula id="10"><atom id="19">n</atom></formula><formula id="11"><impl><atom id="19">n</atom><atom id="18">np</atom></impl></formula><formula id="12"><impl><atom id="18">np</atom><impl><atom id="12">np</atom><atom id="16">np</atom></impl></impl></formula><formula id="13"><atom id="13">n</atom></formula><formula id="14"><impl><atom id="13">n</atom><atom id="10">np</atom></impl></formula><formula id="15"><impl><atom id="10">np</atom><atom id="12">np</atom></impl></formula><formula id="16"><impl><atom id="33">ssub</atom><impl><atom id="1">smain</atom><atom id="8">smain</atom></impl></impl></formula><formula id="17"><atom id="42">vz</atom></formula><formula id="18"><impl><atom id="42">vz</atom><impl><atom id="45">np</atom><impl><atom id="39">np</atom><atom id="37">smain</atom></impl></impl></impl></formula><formula id="19"><impl><atom id="48">np</atom><atom id="53">np</atom></impl></formula><formula id="20"><impl><impl><atom id="48">np</atom><atom id="53">np</atom></impl><impl><atom id="47">np</atom><atom id="51">np</atom></impl></impl></formula><formula id="21"><atom id="54">n</atom></formula><formula id="22"><impl><atom id="54">n</atom><atom id="47">np</atom></impl></formula><formula id="23"><impl><atom id="51">np</atom><impl><atom id="77">np</atom><impl><atom id="98">np</atom><atom id="89">np</atom></impl></impl></impl></formula><formula id="24"><atom id="80">ppart</atom></formula><formula id="25"><impl><atom id="80">ppart</atom><atom id="79">ppart</atom></impl></formula><formula id="26"><impl><atom id="79">ppart</atom><atom id="85">inf</atom></impl></formula><formula id="27"><impl><atom id="85">inf</atom><impl><atom id="74">vnw</atom><atom id="83">ssub</atom></impl></impl></formula><formula id="28"><impl><impl><atom id="74">vnw</atom><atom id="83">ssub</atom></impl><impl><atom id="70">np</atom><atom id="77">np</atom></impl></impl></formula><formula id="29"><atom id="73">n</atom></formula><formula id="30"><impl><atom id="73">n</atom><atom id="72">np</atom></impl></formula><formula id="31"><impl><atom id="72">np</atom><impl><atom id="61">np</atom><atom id="70">np</atom></impl></impl></formula><formula id="32"><atom id="64">n</atom></formula><formula id="33"><impl><atom id="64">n</atom><atom id="63">np</atom></impl></formula><formula id="34"><impl><atom id="63">np</atom><impl><impl><atom id="58">np</atom><atom id="66">np</atom></impl><impl><atom id="56">np</atom><atom id="61">np</atom></impl></impl></impl></formula><formula id="35"><impl><atom id="58">np</atom><atom id="66">np</atom></impl></formula><formula id="36"><atom id="67">adj</atom></formula><formula id="37"><impl><atom id="67">adj</atom><atom id="56">np</atom></impl></formula><formula id="38"><atom id="109">n</atom></formula><formula id="39"><impl><atom id="109">n</atom><atom id="108">np</atom></impl></formula><formula id="40"><impl><atom id="108">np</atom><impl><atom id="102">np</atom><atom id="106">np</atom></impl></impl></formula><formula id="41"><atom id="103">n</atom></formula><formula id="42"><impl><atom id="103">n</atom><atom id="100">np</atom></impl></formula><formula id="43"><impl><atom id="100">np</atom><atom id="102">np</atom></impl></formula><formula id="44"><impl><atom id="106">np</atom><atom id="116">inf</atom></impl></formula><formula id="45"><impl><atom id="116">inf</atom><atom id="114">inf</atom></impl></formula><formula id="46"><impl><atom id="114">inf</atom><impl><atom id="95">vnw</atom><atom id="112">ssub</atom></impl></impl></formula><formula id="47"><impl><impl><atom id="95">vnw</atom><atom id="112">ssub</atom></impl><impl><atom id="93">np</atom><atom id="98">np</atom></impl></impl></formula><formula id="48"><atom id="94">n</atom></formula><formula id="49"><impl><atom id="94">n</atom><atom id="91">np</atom></impl></formula><formula id="50"><impl><atom id="91">np</atom><atom id="93">np</atom></impl></formula><formula id="51"><impl><atom id="89">np</atom><impl><atom id="41">np</atom><atom id="45">np</atom></impl></impl></formula><formula id="52"><atom id="41">np</atom></formula><formula id="53"><atom id="40">n</atom></formula><formula id="54"><impl><atom id="40">n</atom><atom id="39">np</atom></impl></formula></antecedent><formula><atom id="4">smain</atom></formula><premisses>
   <rule name="ax"><antecedent><formula id="1"><atom id="5">n</atom></formula></antecedent><formula><atom id="5">n</atom></formula><premisses></premisses></rule>,
   <rule name="il"><antecedent><formula id="1"><atom id="30">ww</atom></formula><formula id="2"><impl><atom id="30">ww</atom><impl><atom id="22">np</atom><atom id="33">ssub</atom></impl></impl></formula><formula id="3"><atom id="29">tw</atom></formula><formula id="4"><impl><atom id="29">tw</atom><impl><atom id="24">np</atom><atom id="28">np</atom></impl></impl></formula><formula id="5"><atom id="25">n</atom></formula><formula id="6"><impl><atom id="25">n</atom><atom id="24">np</atom></impl></formula><formula id="7"><impl><atom id="28">np</atom><impl><atom id="16">np</atom><atom id="22">np</atom></impl></impl></formula><formula id="8"><atom id="19">n</atom></formula><formula id="9"><impl><atom id="19">n</atom><atom id="18">np</atom></impl></formula><formula id="10"><impl><atom id="18">np</atom><impl><atom id="12">np</atom><atom id="16">np</atom></impl></impl></formula><formula id="11"><atom id="13">n</atom></formula><formula id="12"><impl><atom id="13">n</atom><atom id="10">np</atom></impl></formula><formula id="13"><impl><atom id="10">np</atom><atom id="12">np</atom></impl></formula><formula id="14"><impl><atom id="33">ssub</atom><impl><atom id="1">smain</atom><atom id="8">smain</atom></impl></impl></formula><formula id="15"><impl><impl><atom id="1">smain</atom><atom id="8">smain</atom></impl><impl><atom id="37">smain</atom><atom id="4">smain</atom></impl></impl></formula><formula id="16"><atom id="42">vz</atom></formula><formula id="17"><impl><atom id="42">vz</atom><impl><atom id="45">np</atom><impl><atom id="39">np</atom><atom id="37">smain</atom></impl></impl></impl></formula><formula id="18"><impl><atom id="48">np</atom><atom id="53">np</atom></impl></formula><formula id="19"><impl><impl><atom id="48">np</atom><atom id="53">np</atom></impl><impl><atom id="47">np</atom><atom id="51">np</atom></impl></impl></formula><formula id="20"><atom id="54">n</atom></formula><formula id="21"><impl><atom id="54">n</atom><atom id="47">np</atom></impl></formula><formula id="22"><impl><atom id="51">np</atom><impl><atom id="77">np</atom><impl><atom id="98">np</atom><atom id="89">np</atom></impl></impl></impl></formula><formula id="23"><atom id="80">ppart</atom></formula><formula id="24"><impl><atom id="80">ppart</atom><atom id="79">ppart</atom></impl></formula><formula id="25"><impl><atom id="79">ppart</atom><atom id="85">inf</atom></impl></formula><formula id="26"><impl><atom id="85">inf</atom><impl><atom id="74">vnw</atom><atom id="83">ssub</atom></impl></impl></formula><formula id="27"><impl><impl><atom id="74">vnw</atom><atom id="83">ssub</atom></impl><impl><atom id="70">np</atom><atom id="77">np</atom></impl></impl></formula><formula id="28"><atom id="73">n</atom></formula><formula id="29"><impl><atom id="73">n</atom><atom id="72">np</atom></impl></formula><formula id="30"><impl><atom id="72">np</atom><impl><atom id="61">np</atom><atom id="70">np</atom></impl></impl></formula><formula id="31"><atom id="64">n</atom></formula><formula id="32"><impl><atom id="64">n</atom><atom id="63">np</atom></impl></formula><formula id="33"><impl><atom id="63">np</atom><impl><impl><atom id="58">np</atom><atom id="66">np</atom></impl><impl><atom id="56">np</atom><atom id="61">np</atom></impl></impl></impl></formula><formula id="34"><impl><atom id="58">np</atom><atom id="66">np</atom></impl></formula><formula id="35"><atom id="67">adj</atom></formula><formula id="36"><impl><atom id="67">adj</atom><atom id="56">np</atom></impl></formula><formula id="37"><atom id="109">n</atom></formula><formula id="38"><impl><atom id="109">n</atom><atom id="108">np</atom></impl></formula><formula id="39"><impl><atom id="108">np</atom><impl><atom id="102">np</atom><atom id="106">np</atom></impl></impl></formula><formula id="40"><atom id="103">n</atom></formula><formula id="41"><impl><atom id="103">n</atom><atom id="100">np</atom></impl></formula><formula id="42"><impl><atom id="100">np</atom><atom id="102">np</atom></impl></formula><formula id="43"><impl><atom id="106">np</atom><atom id="116">inf</atom></impl></formula><formula id="44"><impl><atom id="116">inf</atom><atom id="114">inf</atom></impl></formula><formula id="45"><impl><atom id="114">inf</atom><impl><atom id="95">vnw</atom><atom id="112">ssub</atom></impl></impl></formula><formula id="46"><impl><impl><atom id="95">vnw</atom><atom id="112">ssub</atom></impl><impl><atom id="93">np</atom><atom id="98">np</atom></impl></impl></formula><formula id="47"><atom id="94">n</atom></formula><formula id="48"><impl><atom id="94">n</atom><atom id="91">np</atom></impl></formula><formula id="49"><impl><atom id="91">np</atom><atom id="93">np</atom></impl></formula><formula id="50"><impl><atom id="89">np</atom><impl><atom id="41">np</atom><atom id="45">np</atom></impl></impl></formula><formula id="51"><atom id="41">np</atom></formula><formula id="52"><atom id="40">n</atom></formula><formula id="53"><impl><atom id="40">n</atom><atom id="39">np</atom></impl></formula></antecedent><formula><atom id="4">smain</atom></formula><premisses>
      <rule name="ir"><antecedent><formula id="1"><atom id="30">ww</atom></formula><formula id="2"><impl><atom id="30">ww</atom><impl><atom id="22">np</atom><atom id="33">ssub</atom></impl></impl></formula><formula id="3"><atom id="29">tw</atom></formula><formula id="4"><impl><atom id="29">tw</atom><impl><atom id="24">np</atom><atom id="28">np</atom></impl></impl></formula><formula id="5"><atom id="25">n</atom></formula><formula id="6"><impl><atom id="25">n</atom><atom id="24">np</atom></impl></formula><formula id="7"><impl><atom id="28">np</atom><impl><atom id="16">np</atom><atom id="22">np</atom></impl></impl></formula><formula id="8"><atom id="19">n</atom></formula><formula id="9"><impl><atom id="19">n</atom><atom id="18">np</atom></impl></formula><formula id="10"><impl><atom id="18">np</atom><impl><atom id="12">np</atom><atom id="16">np</atom></impl></impl></formula><formula id="11"><atom id="13">n</atom></formula><formula id="12"><impl><atom id="13">n</atom><atom id="10">np</atom></impl></formula><formula id="13"><impl><atom id="10">np</atom><atom id="12">np</atom></impl></formula><formula id="14"><impl><atom id="33">ssub</atom><impl><atom id="1">smain</atom><atom id="8">smain</atom></impl></impl></formula></antecedent><formula><impl><atom id="1">smain</atom><atom id="8">smain</atom></impl></formula><premisses>
         <rule name="il"><antecedent><formula id="1"><atom id="30">ww</atom></formula><formula id="2"><impl><atom id="30">ww</atom><impl><atom id="22">np</atom><atom id="33">ssub</atom></impl></impl></formula><formula id="3"><atom id="29">tw</atom></formula><formula id="4"><impl><atom id="29">tw</atom><impl><atom id="24">np</atom><atom id="28">np</atom></impl></impl></formula><formula id="5"><atom id="25">n</atom></formula><formula id="6"><impl><atom id="25">n</atom><atom id="24">np</atom></impl></formula><formula id="7"><impl><atom id="28">np</atom><impl><atom id="16">np</atom><atom id="22">np</atom></impl></impl></formula><formula id="8"><atom id="19">n</atom></formula><formula id="9"><impl><atom id="19">n</atom><atom id="18">np</atom></impl></formula><formula id="10"><impl><atom id="18">np</atom><impl><atom id="12">np</atom><atom id="16">np</atom></impl></impl></formula><formula id="11"><atom id="13">n</atom></formula><formula id="12"><impl><atom id="13">n</atom><atom id="10">np</atom></impl></formula><formula id="13"><impl><atom id="10">np</atom><atom id="12">np</atom></impl></formula><formula id="14"><impl><atom id="33">ssub</atom><impl><atom id="1">smain</atom><atom id="8">smain</atom></impl></impl></formula><formula id="15"><atom id="1">smain</atom></formula></antecedent><formula><atom id="8">smain</atom></formula><premisses>
            <rule name="il"><antecedent><formula id="1"><atom id="30">ww</atom></formula><formula id="2"><impl><atom id="30">ww</atom><impl><atom id="22">np</atom><atom id="33">ssub</atom></impl></impl></formula><formula id="3"><atom id="29">tw</atom></formula><formula id="4"><impl><atom id="29">tw</atom><impl><atom id="24">np</atom><atom id="28">np</atom></impl></impl></formula><formula id="5"><atom id="25">n</atom></formula><formula id="6"><impl><atom id="25">n</atom><atom id="24">np</atom></impl></formula><formula id="7"><impl><atom id="28">np</atom><impl><atom id="16">np</atom><atom id="22">np</atom></impl></impl></formula><formula id="8"><atom id="19">n</atom></formula><formula id="9"><impl><atom id="19">n</atom><atom id="18">np</atom></impl></formula><formula id="10"><impl><atom id="18">np</atom><impl><atom id="12">np</atom><atom id="16">np</atom></impl></impl></formula><formula id="11"><atom id="13">n</atom></formula><formula id="12"><impl><atom id="13">n</atom><atom id="10">np</atom></impl></formula><formula id="13"><impl><atom id="10">np</atom><atom id="12">np</atom></impl></formula></antecedent><formula><atom id="33">ssub</atom></formula><premisses>
               <rule name="ax"><antecedent><formula id="1"><atom id="30">ww</atom></formula></antecedent><formula><atom id="30">ww</atom></formula><premisses></premisses></rule>,
               <rule name="il"><antecedent><formula id="1"><atom id="29">tw</atom></formula><formula id="2"><impl><atom id="29">tw</atom><impl><atom id="24">np</atom><atom id="28">np</atom></impl></impl></formula><formula id="3"><atom id="25">n</atom></formula><formula id="4"><impl><atom id="25">n</atom><atom id="24">np</atom></impl></formula><formula id="5"><impl><atom id="28">np</atom><impl><atom id="16">np</atom><atom id="22">np</atom></impl></impl></formula><formula id="6"><atom id="19">n</atom></formula><formula id="7"><impl><atom id="19">n</atom><atom id="18">np</atom></impl></formula><formula id="8"><impl><atom id="18">np</atom><impl><atom id="12">np</atom><atom id="16">np</atom></impl></impl></formula><formula id="9"><atom id="13">n</atom></formula><formula id="10"><impl><atom id="13">n</atom><atom id="10">np</atom></impl></formula><formula id="11"><impl><atom id="10">np</atom><atom id="12">np</atom></impl></formula><formula id="12"><impl><atom id="22">np</atom><atom id="33">ssub</atom></impl></formula></antecedent><formula><atom id="33">ssub</atom></formula><premisses>
                  <rule name="il"><antecedent><formula id="1"><atom id="29">tw</atom></formula><formula id="2"><impl><atom id="29">tw</atom><impl><atom id="24">np</atom><atom id="28">np</atom></impl></impl></formula><formula id="3"><atom id="25">n</atom></formula><formula id="4"><impl><atom id="25">n</atom><atom id="24">np</atom></impl></formula><formula id="5"><impl><atom id="28">np</atom><impl><atom id="16">np</atom><atom id="22">np</atom></impl></impl></formula><formula id="6"><atom id="19">n</atom></formula><formula id="7"><impl><atom id="19">n</atom><atom id="18">np</atom></impl></formula><formula id="8"><impl><atom id="18">np</atom><impl><atom id="12">np</atom><atom id="16">np</atom></impl></impl></formula><formula id="9"><atom id="13">n</atom></formula><formula id="10"><impl><atom id="13">n</atom><atom id="10">np</atom></impl></formula><formula id="11"><impl><atom id="10">np</atom><atom id="12">np</atom></impl></formula></antecedent><formula><atom id="22">np</atom></formula><premisses>
                     <rule name="il"><antecedent><formula id="1"><atom id="29">tw</atom></formula><formula id="2"><impl><atom id="29">tw</atom><impl><atom id="24">np</atom><atom id="28">np</atom></impl></impl></formula><formula id="3"><atom id="25">n</atom></formula><formula id="4"><impl><atom id="25">n</atom><atom id="24">np</atom></impl></formula></antecedent><formula><atom id="28">np</atom></formula><premisses>
                        <rule name="ax"><antecedent><formula id="1"><atom id="29">tw</atom></formula></antecedent><formula><atom id="29">tw</atom></formula><premisses></premisses></rule>,
                        <rule name="il"><antecedent><formula id="1"><atom id="25">n</atom></formula><formula id="2"><impl><atom id="25">n</atom><atom id="24">np</atom></impl></formula><formula id="3"><impl><atom id="24">np</atom><atom id="28">np</atom></impl></formula></antecedent><formula><atom id="28">np</atom></formula><premisses>
                           <rule name="il"><antecedent><formula id="1"><atom id="25">n</atom></formula><formula id="2"><impl><atom id="25">n</atom><atom id="24">np</atom></impl></formula></antecedent><formula><atom id="24">np</atom></formula><premisses>
                              <rule name="ax"><antecedent><formula id="1"><atom id="25">n</atom></formula></antecedent><formula><atom id="25">n</atom></formula><premisses></premisses></rule>,
                              <rule name="ax"><antecedent><formula id="1"><atom id="24">np</atom></formula></antecedent><formula><atom id="24">np</atom></formula><premisses></premisses></rule>
                              </premisses></rule>,
                           <rule name="ax"><antecedent><formula id="1"><atom id="28">np</atom></formula></antecedent><formula><atom id="28">np</atom></formula><premisses></premisses></rule>
                           </premisses></rule>
                        </premisses></rule>,
                     <rule name="il"><antecedent><formula id="1"><atom id="19">n</atom></formula><formula id="2"><impl><atom id="19">n</atom><atom id="18">np</atom></impl></formula><formula id="3"><impl><atom id="18">np</atom><impl><atom id="12">np</atom><atom id="16">np</atom></impl></impl></formula><formula id="4"><atom id="13">n</atom></formula><formula id="5"><impl><atom id="13">n</atom><atom id="10">np</atom></impl></formula><formula id="6"><impl><atom id="10">np</atom><atom id="12">np</atom></impl></formula><formula id="7"><impl><atom id="16">np</atom><atom id="22">np</atom></impl></formula></antecedent><formula><atom id="22">np</atom></formula><premisses>
                        <rule name="il"><antecedent><formula id="1"><atom id="19">n</atom></formula><formula id="2"><impl><atom id="19">n</atom><atom id="18">np</atom></impl></formula><formula id="3"><impl><atom id="18">np</atom><impl><atom id="12">np</atom><atom id="16">np</atom></impl></impl></formula><formula id="4"><atom id="13">n</atom></formula><formula id="5"><impl><atom id="13">n</atom><atom id="10">np</atom></impl></formula><formula id="6"><impl><atom id="10">np</atom><atom id="12">np</atom></impl></formula></antecedent><formula><atom id="16">np</atom></formula><premisses>
                           <rule name="il"><antecedent><formula id="1"><atom id="19">n</atom></formula><formula id="2"><impl><atom id="19">n</atom><atom id="18">np</atom></impl></formula></antecedent><formula><atom id="18">np</atom></formula><premisses>
                              <rule name="ax"><antecedent><formula id="1"><atom id="19">n</atom></formula></antecedent><formula><atom id="19">n</atom></formula><premisses></premisses></rule>,
                              <rule name="ax"><antecedent><formula id="1"><atom id="18">np</atom></formula></antecedent><formula><atom id="18">np</atom></formula><premisses></premisses></rule>
                              </premisses></rule>,
                           <rule name="il"><antecedent><formula id="1"><atom id="13">n</atom></formula><formula id="2"><impl><atom id="13">n</atom><atom id="10">np</atom></impl></formula><formula id="3"><impl><atom id="10">np</atom><atom id="12">np</atom></impl></formula><formula id="4"><impl><atom id="12">np</atom><atom id="16">np</atom></impl></formula></antecedent><formula><atom id="16">np</atom></formula><premisses>
                              <rule name="il"><antecedent><formula id="1"><atom id="13">n</atom></formula><formula id="2"><impl><atom id="13">n</atom><atom id="10">np</atom></impl></formula><formula id="3"><impl><atom id="10">np</atom><atom id="12">np</atom></impl></formula></antecedent><formula><atom id="12">np</atom></formula><premisses>
                                 <rule name="il"><antecedent><formula id="1"><atom id="13">n</atom></formula><formula id="2"><impl><atom id="13">n</atom><atom id="10">np</atom></impl></formula></antecedent><formula><atom id="10">np</atom></formula><premisses>
                                    <rule name="ax"><antecedent><formula id="1"><atom id="13">n</atom></formula></antecedent><formula><atom id="13">n</atom></formula><premisses></premisses></rule>,
                                    <rule name="ax"><antecedent><formula id="1"><atom id="10">np</atom></formula></antecedent><formula><atom id="10">np</atom></formula><premisses></premisses></rule>
                                    </premisses></rule>,
                                 <rule name="ax"><antecedent><formula id="1"><atom id="12">np</atom></formula></antecedent><formula><atom id="12">np</atom></formula><premisses></premisses></rule>
                                 </premisses></rule>,
                              <rule name="ax"><antecedent><formula id="1"><atom id="16">np</atom></formula></antecedent><formula><atom id="16">np</atom></formula><premisses></premisses></rule>
                              </premisses></rule>
                           </premisses></rule>,
                        <rule name="ax"><antecedent><formula id="1"><atom id="22">np</atom></formula></antecedent><formula><atom id="22">np</atom></formula><premisses></premisses></rule>
                        </premisses></rule>
                     </premisses></rule>,
                  <rule name="ax"><antecedent><formula id="1"><atom id="33">ssub</atom></formula></antecedent><formula><atom id="33">ssub</atom></formula><premisses></premisses></rule>
                  </premisses></rule>
               </premisses></rule>,
            <rule name="il"><antecedent><formula id="1"><atom id="1">smain</atom></formula><formula id="2"><impl><atom id="1">smain</atom><atom id="8">smain</atom></impl></formula></antecedent><formula><atom id="8">smain</atom></formula><premisses>
               <rule name="ax"><antecedent><formula id="1"><atom id="1">smain</atom></formula></antecedent><formula><atom id="1">smain</atom></formula><premisses></premisses></rule>,
               <rule name="ax"><antecedent><formula id="1"><atom id="8">smain</atom></formula></antecedent><formula><atom id="8">smain</atom></formula><premisses></premisses></rule>
               </premisses></rule>
            </premisses></rule>
         </premisses></rule>,
      <rule name="il"><antecedent><formula id="1"><atom id="42">vz</atom></formula><formula id="2"><impl><atom id="42">vz</atom><impl><atom id="45">np</atom><impl><atom id="39">np</atom><atom id="37">smain</atom></impl></impl></impl></formula><formula id="3"><impl><atom id="48">np</atom><atom id="53">np</atom></impl></formula><formula id="4"><impl><impl><atom id="48">np</atom><atom id="53">np</atom></impl><impl><atom id="47">np</atom><atom id="51">np</atom></impl></impl></formula><formula id="5"><atom id="54">n</atom></formula><formula id="6"><impl><atom id="54">n</atom><atom id="47">np</atom></impl></formula><formula id="7"><impl><atom id="51">np</atom><impl><atom id="77">np</atom><impl><atom id="98">np</atom><atom id="89">np</atom></impl></impl></impl></formula><formula id="8"><atom id="80">ppart</atom></formula><formula id="9"><impl><atom id="80">ppart</atom><atom id="79">ppart</atom></impl></formula><formula id="10"><impl><atom id="79">ppart</atom><atom id="85">inf</atom></impl></formula><formula id="11"><impl><atom id="85">inf</atom><impl><atom id="74">vnw</atom><atom id="83">ssub</atom></impl></impl></formula><formula id="12"><impl><impl><atom id="74">vnw</atom><atom id="83">ssub</atom></impl><impl><atom id="70">np</atom><atom id="77">np</atom></impl></impl></formula><formula id="13"><atom id="73">n</atom></formula><formula id="14"><impl><atom id="73">n</atom><atom id="72">np</atom></impl></formula><formula id="15"><impl><atom id="72">np</atom><impl><atom id="61">np</atom><atom id="70">np</atom></impl></impl></formula><formula id="16"><atom id="64">n</atom></formula><formula id="17"><impl><atom id="64">n</atom><atom id="63">np</atom></impl></formula><formula id="18"><impl><atom id="63">np</atom><impl><impl><atom id="58">np</atom><atom id="66">np</atom></impl><impl><atom id="56">np</atom><atom id="61">np</atom></impl></impl></impl></formula><formula id="19"><impl><atom id="58">np</atom><atom id="66">np</atom></impl></formula><formula id="20"><atom id="67">adj</atom></formula><formula id="21"><impl><atom id="67">adj</atom><atom id="56">np</atom></impl></formula><formula id="22"><atom id="109">n</atom></formula><formula id="23"><impl><atom id="109">n</atom><atom id="108">np</atom></impl></formula><formula id="24"><impl><atom id="108">np</atom><impl><atom id="102">np</atom><atom id="106">np</atom></impl></impl></formula><formula id="25"><atom id="103">n</atom></formula><formula id="26"><impl><atom id="103">n</atom><atom id="100">np</atom></impl></formula><formula id="27"><impl><atom id="100">np</atom><atom id="102">np</atom></impl></formula><formula id="28"><impl><atom id="106">np</atom><atom id="116">inf</atom></impl></formula><formula id="29"><impl><atom id="116">inf</atom><atom id="114">inf</atom></impl></formula><formula id="30"><impl><atom id="114">inf</atom><impl><atom id="95">vnw</atom><atom id="112">ssub</atom></impl></impl></formula><formula id="31"><impl><impl><atom id="95">vnw</atom><atom id="112">ssub</atom></impl><impl><atom id="93">np</atom><atom id="98">np</atom></impl></impl></formula><formula id="32"><atom id="94">n</atom></formula><formula id="33"><impl><atom id="94">n</atom><atom id="91">np</atom></impl></formula><formula id="34"><impl><atom id="91">np</atom><atom id="93">np</atom></impl></formula><formula id="35"><impl><atom id="89">np</atom><impl><atom id="41">np</atom><atom id="45">np</atom></impl></impl></formula><formula id="36"><atom id="41">np</atom></formula><formula id="37"><atom id="40">n</atom></formula><formula id="38"><impl><atom id="40">n</atom><atom id="39">np</atom></impl></formula><formula id="39"><impl><atom id="37">smain</atom><atom id="4">smain</atom></impl></formula></antecedent><formula><atom id="4">smain</atom></formula><premisses>
         <rule name="il"><antecedent><formula id="1"><atom id="42">vz</atom></formula><formula id="2"><impl><atom id="42">vz</atom><impl><atom id="45">np</atom><impl><atom id="39">np</atom><atom id="37">smain</atom></impl></impl></impl></formula><formula id="3"><impl><atom id="48">np</atom><atom id="53">np</atom></impl></formula><formula id="4"><impl><impl><atom id="48">np</atom><atom id="53">np</atom></impl><impl><atom id="47">np</atom><atom id="51">np</atom></impl></impl></formula><formula id="5"><atom id="54">n</atom></formula><formula id="6"><impl><atom id="54">n</atom><atom id="47">np</atom></impl></formula><formula id="7"><impl><atom id="51">np</atom><impl><atom id="77">np</atom><impl><atom id="98">np</atom><atom id="89">np</atom></impl></impl></impl></formula><formula id="8"><atom id="80">ppart</atom></formula><formula id="9"><impl><atom id="80">ppart</atom><atom id="79">ppart</atom></impl></formula><formula id="10"><impl><atom id="79">ppart</atom><atom id="85">inf</atom></impl></formula><formula id="11"><impl><atom id="85">inf</atom><impl><atom id="74">vnw</atom><atom id="83">ssub</atom></impl></impl></formula><formula id="12"><impl><impl><atom id="74">vnw</atom><atom id="83">ssub</atom></impl><impl><atom id="70">np</atom><atom id="77">np</atom></impl></impl></formula><formula id="13"><atom id="73">n</atom></formula><formula id="14"><impl><atom id="73">n</atom><atom id="72">np</atom></impl></formula><formula id="15"><impl><atom id="72">np</atom><impl><atom id="61">np</atom><atom id="70">np</atom></impl></impl></formula><formula id="16"><atom id="64">n</atom></formula><formula id="17"><impl><atom id="64">n</atom><atom id="63">np</atom></impl></formula><formula id="18"><impl><atom id="63">np</atom><impl><impl><atom id="58">np</atom><atom id="66">np</atom></impl><impl><atom id="56">np</atom><atom id="61">np</atom></impl></impl></impl></formula><formula id="19"><impl><atom id="58">np</atom><atom id="66">np</atom></impl></formula><formula id="20"><atom id="67">adj</atom></formula><formula id="21"><impl><atom id="67">adj</atom><atom id="56">np</atom></impl></formula><formula id="22"><atom id="109">n</atom></formula><formula id="23"><impl><atom id="109">n</atom><atom id="108">np</atom></impl></formula><formula id="24"><impl><atom id="108">np</atom><impl><atom id="102">np</atom><atom id="106">np</atom></impl></impl></formula><formula id="25"><atom id="103">n</atom></formula><formula id="26"><impl><atom id="103">n</atom><atom id="100">np</atom></impl></formula><formula id="27"><impl><atom id="100">np</atom><atom id="102">np</atom></impl></formula><formula id="28"><impl><atom id="106">np</atom><atom id="116">inf</atom></impl></formula><formula id="29"><impl><atom id="116">inf</atom><atom id="114">inf</atom></impl></formula><formula id="30"><impl><atom id="114">inf</atom><impl><atom id="95">vnw</atom><atom id="112">ssub</atom></impl></impl></formula><formula id="31"><impl><impl><atom id="95">vnw</atom><atom id="112">ssub</atom></impl><impl><atom id="93">np</atom><atom id="98">np</atom></impl></impl></formula><formula id="32"><atom id="94">n</atom></formula><formula id="33"><impl><atom id="94">n</atom><atom id="91">np</atom></impl></formula><formula id="34"><impl><atom id="91">np</atom><atom id="93">np</atom></impl></formula><formula id="35"><impl><atom id="89">np</atom><impl><atom id="41">np</atom><atom id="45">np</atom></impl></impl></formula><formula id="36"><atom id="41">np</atom></formula><formula id="37"><atom id="40">n</atom></formula><formula id="38"><impl><atom id="40">n</atom><atom id="39">np</atom></impl></formula></antecedent><formula><atom id="37">smain</atom></formula><premisses>
            <rule name="ax"><antecedent><formula id="1"><atom id="42">vz</atom></formula></antecedent><formula><atom id="42">vz</atom></formula><premisses></premisses></rule>,
            <rule name="il"><antecedent><formula id="1"><impl><atom id="48">np</atom><atom id="53">np</atom></impl></formula><formula id="2"><impl><impl><atom id="48">np</atom><atom id="53">np</atom></impl><impl><atom id="47">np</atom><atom id="51">np</atom></impl></impl></formula><formula id="3"><atom id="54">n</atom></formula><formula id="4"><impl><atom id="54">n</atom><atom id="47">np</atom></impl></formula><formula id="5"><impl><atom id="51">np</atom><impl><atom id="77">np</atom><impl><atom id="98">np</atom><atom id="89">np</atom></impl></impl></impl></formula><formula id="6"><atom id="80">ppart</atom></formula><formula id="7"><impl><atom id="80">ppart</atom><atom id="79">ppart</atom></impl></formula><formula id="8"><impl><atom id="79">ppart</atom><atom id="85">inf</atom></impl></formula><formula id="9"><impl><atom id="85">inf</atom><impl><atom id="74">vnw</atom><atom id="83">ssub</atom></impl></impl></formula><formula id="10"><impl><impl><atom id="74">vnw</atom><atom id="83">ssub</atom></impl><impl><atom id="70">np</atom><atom id="77">np</atom></impl></impl></formula><formula id="11"><atom id="73">n</atom></formula><formula id="12"><impl><atom id="73">n</atom><atom id="72">np</atom></impl></formula><formula id="13"><impl><atom id="72">np</atom><impl><atom id="61">np</atom><atom id="70">np</atom></impl></impl></formula><formula id="14"><atom id="64">n</atom></formula><formula id="15"><impl><atom id="64">n</atom><atom id="63">np</atom></impl></formula><formula id="16"><impl><atom id="63">np</atom><impl><impl><atom id="58">np</atom><atom id="66">np</atom></impl><impl><atom id="56">np</atom><atom id="61">np</atom></impl></impl></impl></formula><formula id="17"><impl><atom id="58">np</atom><atom id="66">np</atom></impl></formula><formula id="18"><atom id="67">adj</atom></formula><formula id="19"><impl><atom id="67">adj</atom><atom id="56">np</atom></impl></formula><formula id="20"><atom id="109">n</atom></formula><formula id="21"><impl><atom id="109">n</atom><atom id="108">np</atom></impl></formula><formula id="22"><impl><atom id="108">np</atom><impl><atom id="102">np</atom><atom id="106">np</atom></impl></impl></formula><formula id="23"><atom id="103">n</atom></formula><formula id="24"><impl><atom id="103">n</atom><atom id="100">np</atom></impl></formula><formula id="25"><impl><atom id="100">np</atom><atom id="102">np</atom></impl></formula><formula id="26"><impl><atom id="106">np</atom><atom id="116">inf</atom></impl></formula><formula id="27"><impl><atom id="116">inf</atom><atom id="114">inf</atom></impl></formula><formula id="28"><impl><atom id="114">inf</atom><impl><atom id="95">vnw</atom><atom id="112">ssub</atom></impl></impl></formula><formula id="29"><impl><impl><atom id="95">vnw</atom><atom id="112">ssub</atom></impl><impl><atom id="93">np</atom><atom id="98">np</atom></impl></impl></formula><formula id="30"><atom id="94">n</atom></formula><formula id="31"><impl><atom id="94">n</atom><atom id="91">np</atom></impl></formula><formula id="32"><impl><atom id="91">np</atom><atom id="93">np</atom></impl></formula><formula id="33"><impl><atom id="89">np</atom><impl><atom id="41">np</atom><atom id="45">np</atom></impl></impl></formula><formula id="34"><atom id="41">np</atom></formula><formula id="35"><impl><atom id="45">np</atom><impl><atom id="39">np</atom><atom id="37">smain</atom></impl></impl></formula><formula id="36"><atom id="40">n</atom></formula><formula id="37"><impl><atom id="40">n</atom><atom id="39">np</atom></impl></formula></antecedent><formula><atom id="37">smain</atom></formula><premisses>
               <rule name="il"><antecedent><formula id="1"><impl><atom id="48">np</atom><atom id="53">np</atom></impl></formula><formula id="2"><impl><impl><atom id="48">np</atom><atom id="53">np</atom></impl><impl><atom id="47">np</atom><atom id="51">np</atom></impl></impl></formula><formula id="3"><atom id="54">n</atom></formula><formula id="4"><impl><atom id="54">n</atom><atom id="47">np</atom></impl></formula><formula id="5"><impl><atom id="51">np</atom><impl><atom id="77">np</atom><impl><atom id="98">np</atom><atom id="89">np</atom></impl></impl></impl></formula><formula id="6"><atom id="80">ppart</atom></formula><formula id="7"><impl><atom id="80">ppart</atom><atom id="79">ppart</atom></impl></formula><formula id="8"><impl><atom id="79">ppart</atom><atom id="85">inf</atom></impl></formula><formula id="9"><impl><atom id="85">inf</atom><impl><atom id="74">vnw</atom><atom id="83">ssub</atom></impl></impl></formula><formula id="10"><impl><impl><atom id="74">vnw</atom><atom id="83">ssub</atom></impl><impl><atom id="70">np</atom><atom id="77">np</atom></impl></impl></formula><formula id="11"><atom id="73">n</atom></formula><formula id="12"><impl><atom id="73">n</atom><atom id="72">np</atom></impl></formula><formula id="13"><impl><atom id="72">np</atom><impl><atom id="61">np</atom><atom id="70">np</atom></impl></impl></formula><formula id="14"><atom id="64">n</atom></formula><formula id="15"><impl><atom id="64">n</atom><atom id="63">np</atom></impl></formula><formula id="16"><impl><atom id="63">np</atom><impl><impl><atom id="58">np</atom><atom id="66">np</atom></impl><impl><atom id="56">np</atom><atom id="61">np</atom></impl></impl></impl></formula><formula id="17"><impl><atom id="58">np</atom><atom id="66">np</atom></impl></formula><formula id="18"><atom id="67">adj</atom></formula><formula id="19"><impl><atom id="67">adj</atom><atom id="56">np</atom></impl></formula><formula id="20"><atom id="109">n</atom></formula><formula id="21"><impl><atom id="109">n</atom><atom id="108">np</atom></impl></formula><formula id="22"><impl><atom id="108">np</atom><impl><atom id="102">np</atom><atom id="106">np</atom></impl></impl></formula><formula id="23"><atom id="103">n</atom></formula><formula id="24"><impl><atom id="103">n</atom><atom id="100">np</atom></impl></formula><formula id="25"><impl><atom id="100">np</atom><atom id="102">np</atom></impl></formula><formula id="26"><impl><atom id="106">np</atom><atom id="116">inf</atom></impl></formula><formula id="27"><impl><atom id="116">inf</atom><atom id="114">inf</atom></impl></formula><formula id="28"><impl><atom id="114">inf</atom><impl><atom id="95">vnw</atom><atom id="112">ssub</atom></impl></impl></formula><formula id="29"><impl><impl><atom id="95">vnw</atom><atom id="112">ssub</atom></impl><impl><atom id="93">np</atom><atom id="98">np</atom></impl></impl></formula><formula id="30"><atom id="94">n</atom></formula><formula id="31"><impl><atom id="94">n</atom><atom id="91">np</atom></impl></formula><formula id="32"><impl><atom id="91">np</atom><atom id="93">np</atom></impl></formula><formula id="33"><impl><atom id="89">np</atom><impl><atom id="41">np</atom><atom id="45">np</atom></impl></impl></formula><formula id="34"><atom id="41">np</atom></formula></antecedent><formula><atom id="45">np</atom></formula><premisses>
                  <rule name="il"><antecedent><formula id="1"><impl><atom id="48">np</atom><atom id="53">np</atom></impl></formula><formula id="2"><impl><impl><atom id="48">np</atom><atom id="53">np</atom></impl><impl><atom id="47">np</atom><atom id="51">np</atom></impl></impl></formula><formula id="3"><atom id="54">n</atom></formula><formula id="4"><impl><atom id="54">n</atom><atom id="47">np</atom></impl></formula><formula id="5"><impl><atom id="51">np</atom><impl><atom id="77">np</atom><impl><atom id="98">np</atom><atom id="89">np</atom></impl></impl></impl></formula><formula id="6"><atom id="80">ppart</atom></formula><formula id="7"><impl><atom id="80">ppart</atom><atom id="79">ppart</atom></impl></formula><formula id="8"><impl><atom id="79">ppart</atom><atom id="85">inf</atom></impl></formula><formula id="9"><impl><atom id="85">inf</atom><impl><atom id="74">vnw</atom><atom id="83">ssub</atom></impl></impl></formula><formula id="10"><impl><impl><atom id="74">vnw</atom><atom id="83">ssub</atom></impl><impl><atom id="70">np</atom><atom id="77">np</atom></impl></impl></formula><formula id="11"><atom id="73">n</atom></formula><formula id="12"><impl><atom id="73">n</atom><atom id="72">np</atom></impl></formula><formula id="13"><impl><atom id="72">np</atom><impl><atom id="61">np</atom><atom id="70">np</atom></impl></impl></formula><formula id="14"><atom id="64">n</atom></formula><formula id="15"><impl><atom id="64">n</atom><atom id="63">np</atom></impl></formula><formula id="16"><impl><atom id="63">np</atom><impl><impl><atom id="58">np</atom><atom id="66">np</atom></impl><impl><atom id="56">np</atom><atom id="61">np</atom></impl></impl></impl></formula><formula id="17"><impl><atom id="58">np</atom><atom id="66">np</atom></impl></formula><formula id="18"><atom id="67">adj</atom></formula><formula id="19"><impl><atom id="67">adj</atom><atom id="56">np</atom></impl></formula><formula id="20"><atom id="109">n</atom></formula><formula id="21"><impl><atom id="109">n</atom><atom id="108">np</atom></impl></formula><formula id="22"><impl><atom id="108">np</atom><impl><atom id="102">np</atom><atom id="106">np</atom></impl></impl></formula><formula id="23"><atom id="103">n</atom></formula><formula id="24"><impl><atom id="103">n</atom><atom id="100">np</atom></impl></formula><formula id="25"><impl><atom id="100">np</atom><atom id="102">np</atom></impl></formula><formula id="26"><impl><atom id="106">np</atom><atom id="116">inf</atom></impl></formula><formula id="27"><impl><atom id="116">inf</atom><atom id="114">inf</atom></impl></formula><formula id="28"><impl><atom id="114">inf</atom><impl><atom id="95">vnw</atom><atom id="112">ssub</atom></impl></impl></formula><formula id="29"><impl><impl><atom id="95">vnw</atom><atom id="112">ssub</atom></impl><impl><atom id="93">np</atom><atom id="98">np</atom></impl></impl></formula><formula id="30"><atom id="94">n</atom></formula><formula id="31"><impl><atom id="94">n</atom><atom id="91">np</atom></impl></formula><formula id="32"><impl><atom id="91">np</atom><atom id="93">np</atom></impl></formula></antecedent><formula><atom id="89">np</atom></formula><premisses>
                     <rule name="il"><antecedent><formula id="1"><impl><atom id="48">np</atom><atom id="53">np</atom></impl></formula><formula id="2"><impl><impl><atom id="48">np</atom><atom id="53">np</atom></impl><impl><atom id="47">np</atom><atom id="51">np</atom></impl></impl></formula><formula id="3"><atom id="54">n</atom></formula><formula id="4"><impl><atom id="54">n</atom><atom id="47">np</atom></impl></formula></antecedent><formula><atom id="51">np</atom></formula><premisses>
                        <rule name="ir"><antecedent><formula id="1"><impl><atom id="48">np</atom><atom id="53">np</atom></impl></formula></antecedent><formula><impl><atom id="48">np</atom><atom id="53">np</atom></impl></formula><premisses>
                           <rule name="il"><antecedent><formula id="1"><atom id="48">np</atom></formula><formula id="2"><impl><atom id="48">np</atom><atom id="53">np</atom></impl></formula></antecedent><formula><atom id="53">np</atom></formula><premisses>
                              <rule name="ax"><antecedent><formula id="1"><atom id="48">np</atom></formula></antecedent><formula><atom id="48">np</atom></formula><premisses></premisses></rule>,
                              <rule name="ax"><antecedent><formula id="1"><atom id="53">np</atom></formula></antecedent><formula><atom id="53">np</atom></formula><premisses></premisses></rule>
                              </premisses></rule>
                           </premisses></rule>,
                        <rule name="il"><antecedent><formula id="1"><atom id="54">n</atom></formula><formula id="2"><impl><atom id="54">n</atom><atom id="47">np</atom></impl></formula><formula id="3"><impl><atom id="47">np</atom><atom id="51">np</atom></impl></formula></antecedent><formula><atom id="51">np</atom></formula><premisses>
                           <rule name="il"><antecedent><formula id="1"><atom id="54">n</atom></formula><formula id="2"><impl><atom id="54">n</atom><atom id="47">np</atom></impl></formula></antecedent><formula><atom id="47">np</atom></formula><premisses>
                              <rule name="ax"><antecedent><formula id="1"><atom id="54">n</atom></formula></antecedent><formula><atom id="54">n</atom></formula><premisses></premisses></rule>,
                              <rule name="ax"><antecedent><formula id="1"><atom id="47">np</atom></formula></antecedent><formula><atom id="47">np</atom></formula><premisses></premisses></rule>
                              </premisses></rule>,
                           <rule name="ax"><antecedent><formula id="1"><atom id="51">np</atom></formula></antecedent><formula><atom id="51">np</atom></formula><premisses></premisses></rule>
                           </premisses></rule>
                        </premisses></rule>,
                     <rule name="il"><antecedent><formula id="1"><atom id="80">ppart</atom></formula><formula id="2"><impl><atom id="80">ppart</atom><atom id="79">ppart</atom></impl></formula><formula id="3"><impl><atom id="79">ppart</atom><atom id="85">inf</atom></impl></formula><formula id="4"><impl><atom id="85">inf</atom><impl><atom id="74">vnw</atom><atom id="83">ssub</atom></impl></impl></formula><formula id="5"><impl><impl><atom id="74">vnw</atom><atom id="83">ssub</atom></impl><impl><atom id="70">np</atom><atom id="77">np</atom></impl></impl></formula><formula id="6"><atom id="73">n</atom></formula><formula id="7"><impl><atom id="73">n</atom><atom id="72">np</atom></impl></formula><formula id="8"><impl><atom id="72">np</atom><impl><atom id="61">np</atom><atom id="70">np</atom></impl></impl></formula><formula id="9"><atom id="64">n</atom></formula><formula id="10"><impl><atom id="64">n</atom><atom id="63">np</atom></impl></formula><formula id="11"><impl><atom id="63">np</atom><impl><impl><atom id="58">np</atom><atom id="66">np</atom></impl><impl><atom id="56">np</atom><atom id="61">np</atom></impl></impl></impl></formula><formula id="12"><impl><atom id="58">np</atom><atom id="66">np</atom></impl></formula><formula id="13"><atom id="67">adj</atom></formula><formula id="14"><impl><atom id="67">adj</atom><atom id="56">np</atom></impl></formula><formula id="15"><impl><atom id="77">np</atom><impl><atom id="98">np</atom><atom id="89">np</atom></impl></impl></formula><formula id="16"><atom id="109">n</atom></formula><formula id="17"><impl><atom id="109">n</atom><atom id="108">np</atom></impl></formula><formula id="18"><impl><atom id="108">np</atom><impl><atom id="102">np</atom><atom id="106">np</atom></impl></impl></formula><formula id="19"><atom id="103">n</atom></formula><formula id="20"><impl><atom id="103">n</atom><atom id="100">np</atom></impl></formula><formula id="21"><impl><atom id="100">np</atom><atom id="102">np</atom></impl></formula><formula id="22"><impl><atom id="106">np</atom><atom id="116">inf</atom></impl></formula><formula id="23"><impl><atom id="116">inf</atom><atom id="114">inf</atom></impl></formula><formula id="24"><impl><atom id="114">inf</atom><impl><atom id="95">vnw</atom><atom id="112">ssub</atom></impl></impl></formula><formula id="25"><impl><impl><atom id="95">vnw</atom><atom id="112">ssub</atom></impl><impl><atom id="93">np</atom><atom id="98">np</atom></impl></impl></formula><formula id="26"><atom id="94">n</atom></formula><formula id="27"><impl><atom id="94">n</atom><atom id="91">np</atom></impl></formula><formula id="28"><impl><atom id="91">np</atom><atom id="93">np</atom></impl></formula></antecedent><formula><atom id="89">np</atom></formula><premisses>
                        <rule name="il"><antecedent><formula id="1"><atom id="80">ppart</atom></formula><formula id="2"><impl><atom id="80">ppart</atom><atom id="79">ppart</atom></impl></formula><formula id="3"><impl><atom id="79">ppart</atom><atom id="85">inf</atom></impl></formula><formula id="4"><impl><atom id="85">inf</atom><impl><atom id="74">vnw</atom><atom id="83">ssub</atom></impl></impl></formula><formula id="5"><impl><impl><atom id="74">vnw</atom><atom id="83">ssub</atom></impl><impl><atom id="70">np</atom><atom id="77">np</atom></impl></impl></formula><formula id="6"><atom id="73">n</atom></formula><formula id="7"><impl><atom id="73">n</atom><atom id="72">np</atom></impl></formula><formula id="8"><impl><atom id="72">np</atom><impl><atom id="61">np</atom><atom id="70">np</atom></impl></impl></formula><formula id="9"><atom id="64">n</atom></formula><formula id="10"><impl><atom id="64">n</atom><atom id="63">np</atom></impl></formula><formula id="11"><impl><atom id="63">np</atom><impl><impl><atom id="58">np</atom><atom id="66">np</atom></impl><impl><atom id="56">np</atom><atom id="61">np</atom></impl></impl></impl></formula><formula id="12"><impl><atom id="58">np</atom><atom id="66">np</atom></impl></formula><formula id="13"><atom id="67">adj</atom></formula><formula id="14"><impl><atom id="67">adj</atom><atom id="56">np</atom></impl></formula></antecedent><formula><atom id="77">np</atom></formula><premisses>
                           <rule name="ir"><antecedent><formula id="1"><atom id="80">ppart</atom></formula><formula id="2"><impl><atom id="80">ppart</atom><atom id="79">ppart</atom></impl></formula><formula id="3"><impl><atom id="79">ppart</atom><atom id="85">inf</atom></impl></formula><formula id="4"><impl><atom id="85">inf</atom><impl><atom id="74">vnw</atom><atom id="83">ssub</atom></impl></impl></formula></antecedent><formula><impl><atom id="74">vnw</atom><atom id="83">ssub</atom></impl></formula><premisses>
                              <rule name="il"><antecedent><formula id="1"><atom id="80">ppart</atom></formula><formula id="2"><impl><atom id="80">ppart</atom><atom id="79">ppart</atom></impl></formula><formula id="3"><impl><atom id="79">ppart</atom><atom id="85">inf</atom></impl></formula><formula id="4"><impl><atom id="85">inf</atom><impl><atom id="74">vnw</atom><atom id="83">ssub</atom></impl></impl></formula><formula id="5"><atom id="74">vnw</atom></formula></antecedent><formula><atom id="83">ssub</atom></formula><premisses>
                                 <rule name="il"><antecedent><formula id="1"><atom id="80">ppart</atom></formula><formula id="2"><impl><atom id="80">ppart</atom><atom id="79">ppart</atom></impl></formula><formula id="3"><impl><atom id="79">ppart</atom><atom id="85">inf</atom></impl></formula></antecedent><formula><atom id="85">inf</atom></formula><premisses>
                                    <rule name="il"><antecedent><formula id="1"><atom id="80">ppart</atom></formula><formula id="2"><impl><atom id="80">ppart</atom><atom id="79">ppart</atom></impl></formula></antecedent><formula><atom id="79">ppart</atom></formula><premisses>
                                       <rule name="ax"><antecedent><formula id="1"><atom id="80">ppart</atom></formula></antecedent><formula><atom id="80">ppart</atom></formula><premisses></premisses></rule>,
                                       <rule name="ax"><antecedent><formula id="1"><atom id="79">ppart</atom></formula></antecedent><formula><atom id="79">ppart</atom></formula><premisses></premisses></rule>
                                       </premisses></rule>,
                                    <rule name="ax"><antecedent><formula id="1"><atom id="85">inf</atom></formula></antecedent><formula><atom id="85">inf</atom></formula><premisses></premisses></rule>
                                    </premisses></rule>,
                                 <rule name="il"><antecedent><formula id="1"><atom id="74">vnw</atom></formula><formula id="2"><impl><atom id="74">vnw</atom><atom id="83">ssub</atom></impl></formula></antecedent><formula><atom id="83">ssub</atom></formula><premisses>
                                    <rule name="ax"><antecedent><formula id="1"><atom id="74">vnw</atom></formula></antecedent><formula><atom id="74">vnw</atom></formula><premisses></premisses></rule>,
                                    <rule name="ax"><antecedent><formula id="1"><atom id="83">ssub</atom></formula></antecedent><formula><atom id="83">ssub</atom></formula><premisses></premisses></rule>
                                    </premisses></rule>
                                 </premisses></rule>
                              </premisses></rule>,
                           <rule name="il"><antecedent><formula id="1"><atom id="73">n</atom></formula><formula id="2"><impl><atom id="73">n</atom><atom id="72">np</atom></impl></formula><formula id="3"><impl><atom id="72">np</atom><impl><atom id="61">np</atom><atom id="70">np</atom></impl></impl></formula><formula id="4"><atom id="64">n</atom></formula><formula id="5"><impl><atom id="64">n</atom><atom id="63">np</atom></impl></formula><formula id="6"><impl><atom id="63">np</atom><impl><impl><atom id="58">np</atom><atom id="66">np</atom></impl><impl><atom id="56">np</atom><atom id="61">np</atom></impl></impl></impl></formula><formula id="7"><impl><atom id="58">np</atom><atom id="66">np</atom></impl></formula><formula id="8"><atom id="67">adj</atom></formula><formula id="9"><impl><atom id="67">adj</atom><atom id="56">np</atom></impl></formula><formula id="10"><impl><atom id="70">np</atom><atom id="77">np</atom></impl></formula></antecedent><formula><atom id="77">np</atom></formula><premisses>
                              <rule name="il"><antecedent><formula id="1"><atom id="73">n</atom></formula><formula id="2"><impl><atom id="73">n</atom><atom id="72">np</atom></impl></formula><formula id="3"><impl><atom id="72">np</atom><impl><atom id="61">np</atom><atom id="70">np</atom></impl></impl></formula><formula id="4"><atom id="64">n</atom></formula><formula id="5"><impl><atom id="64">n</atom><atom id="63">np</atom></impl></formula><formula id="6"><impl><atom id="63">np</atom><impl><impl><atom id="58">np</atom><atom id="66">np</atom></impl><impl><atom id="56">np</atom><atom id="61">np</atom></impl></impl></impl></formula><formula id="7"><impl><atom id="58">np</atom><atom id="66">np</atom></impl></formula><formula id="8"><atom id="67">adj</atom></formula><formula id="9"><impl><atom id="67">adj</atom><atom id="56">np</atom></impl></formula></antecedent><formula><atom id="70">np</atom></formula><premisses>
                                 <rule name="il"><antecedent><formula id="1"><atom id="73">n</atom></formula><formula id="2"><impl><atom id="73">n</atom><atom id="72">np</atom></impl></formula></antecedent><formula><atom id="72">np</atom></formula><premisses>
                                    <rule name="ax"><antecedent><formula id="1"><atom id="73">n</atom></formula></antecedent><formula><atom id="73">n</atom></formula><premisses></premisses></rule>,
                                    <rule name="ax"><antecedent><formula id="1"><atom id="72">np</atom></formula></antecedent><formula><atom id="72">np</atom></formula><premisses></premisses></rule>
                                    </premisses></rule>,
                                 <rule name="il"><antecedent><formula id="1"><atom id="64">n</atom></formula><formula id="2"><impl><atom id="64">n</atom><atom id="63">np</atom></impl></formula><formula id="3"><impl><atom id="63">np</atom><impl><impl><atom id="58">np</atom><atom id="66">np</atom></impl><impl><atom id="56">np</atom><atom id="61">np</atom></impl></impl></impl></formula><formula id="4"><impl><atom id="58">np</atom><atom id="66">np</atom></impl></formula><formula id="5"><atom id="67">adj</atom></formula><formula id="6"><impl><atom id="67">adj</atom><atom id="56">np</atom></impl></formula><formula id="7"><impl><atom id="61">np</atom><atom id="70">np</atom></impl></formula></antecedent><formula><atom id="70">np</atom></formula><premisses>
                                    <rule name="il"><antecedent><formula id="1"><atom id="64">n</atom></formula><formula id="2"><impl><atom id="64">n</atom><atom id="63">np</atom></impl></formula><formula id="3"><impl><atom id="63">np</atom><impl><impl><atom id="58">np</atom><atom id="66">np</atom></impl><impl><atom id="56">np</atom><atom id="61">np</atom></impl></impl></impl></formula><formula id="4"><impl><atom id="58">np</atom><atom id="66">np</atom></impl></formula><formula id="5"><atom id="67">adj</atom></formula><formula id="6"><impl><atom id="67">adj</atom><atom id="56">np</atom></impl></formula></antecedent><formula><atom id="61">np</atom></formula><premisses>
                                       <rule name="il"><antecedent><formula id="1"><atom id="64">n</atom></formula><formula id="2"><impl><atom id="64">n</atom><atom id="63">np</atom></impl></formula></antecedent><formula><atom id="63">np</atom></formula><premisses>
                                          <rule name="ax"><antecedent><formula id="1"><atom id="64">n</atom></formula></antecedent><formula><atom id="64">n</atom></formula><premisses></premisses></rule>,
                                          <rule name="ax"><antecedent><formula id="1"><atom id="63">np</atom></formula></antecedent><formula><atom id="63">np</atom></formula><premisses></premisses></rule>
                                          </premisses></rule>,
                                       <rule name="il"><antecedent><formula id="1"><impl><atom id="58">np</atom><atom id="66">np</atom></impl></formula><formula id="2"><impl><impl><atom id="58">np</atom><atom id="66">np</atom></impl><impl><atom id="56">np</atom><atom id="61">np</atom></impl></impl></formula><formula id="3"><atom id="67">adj</atom></formula><formula id="4"><impl><atom id="67">adj</atom><atom id="56">np</atom></impl></formula></antecedent><formula><atom id="61">np</atom></formula><premisses>
                                          <rule name="ir"><antecedent><formula id="1"><impl><atom id="58">np</atom><atom id="66">np</atom></impl></formula></antecedent><formula><impl><atom id="58">np</atom><atom id="66">np</atom></impl></formula><premisses>
                                             <rule name="il"><antecedent><formula id="1"><atom id="58">np</atom></formula><formula id="2"><impl><atom id="58">np</atom><atom id="66">np</atom></impl></formula></antecedent><formula><atom id="66">np</atom></formula><premisses>
                                                <rule name="ax"><antecedent><formula id="1"><atom id="58">np</atom></formula></antecedent><formula><atom id="58">np</atom></formula><premisses></premisses></rule>,
                                                <rule name="ax"><antecedent><formula id="1"><atom id="66">np</atom></formula></antecedent><formula><atom id="66">np</atom></formula><premisses></premisses></rule>
                                                </premisses></rule>
                                             </premisses></rule>,
                                          <rule name="il"><antecedent><formula id="1"><atom id="67">adj</atom></formula><formula id="2"><impl><atom id="67">adj</atom><atom id="56">np</atom></impl></formula><formula id="3"><impl><atom id="56">np</atom><atom id="61">np</atom></impl></formula></antecedent><formula><atom id="61">np</atom></formula><premisses>
                                             <rule name="il"><antecedent><formula id="1"><atom id="67">adj</atom></formula><formula id="2"><impl><atom id="67">adj</atom><atom id="56">np</atom></impl></formula></antecedent><formula><atom id="56">np</atom></formula><premisses>
                                                <rule name="ax"><antecedent><formula id="1"><atom id="67">adj</atom></formula></antecedent><formula><atom id="67">adj</atom></formula><premisses></premisses></rule>,
                                                <rule name="ax"><antecedent><formula id="1"><atom id="56">np</atom></formula></antecedent><formula><atom id="56">np</atom></formula><premisses></premisses></rule>
                                                </premisses></rule>,
                                             <rule name="ax"><antecedent><formula id="1"><atom id="61">np</atom></formula></antecedent><formula><atom id="61">np</atom></formula><premisses></premisses></rule>
                                             </premisses></rule>
                                          </premisses></rule>
                                       </premisses></rule>,
                                    <rule name="ax"><antecedent><formula id="1"><atom id="70">np</atom></formula></antecedent><formula><atom id="70">np</atom></formula><premisses></premisses></rule>
                                    </premisses></rule>
                                 </premisses></rule>,
                              <rule name="ax"><antecedent><formula id="1"><atom id="77">np</atom></formula></antecedent><formula><atom id="77">np</atom></formula><premisses></premisses></rule>
                              </premisses></rule>
                           </premisses></rule>,
                        <rule name="il"><antecedent><formula id="1"><atom id="109">n</atom></formula><formula id="2"><impl><atom id="109">n</atom><atom id="108">np</atom></impl></formula><formula id="3"><impl><atom id="108">np</atom><impl><atom id="102">np</atom><atom id="106">np</atom></impl></impl></formula><formula id="4"><atom id="103">n</atom></formula><formula id="5"><impl><atom id="103">n</atom><atom id="100">np</atom></impl></formula><formula id="6"><impl><atom id="100">np</atom><atom id="102">np</atom></impl></formula><formula id="7"><impl><atom id="106">np</atom><atom id="116">inf</atom></impl></formula><formula id="8"><impl><atom id="116">inf</atom><atom id="114">inf</atom></impl></formula><formula id="9"><impl><atom id="114">inf</atom><impl><atom id="95">vnw</atom><atom id="112">ssub</atom></impl></impl></formula><formula id="10"><impl><impl><atom id="95">vnw</atom><atom id="112">ssub</atom></impl><impl><atom id="93">np</atom><atom id="98">np</atom></impl></impl></formula><formula id="11"><atom id="94">n</atom></formula><formula id="12"><impl><atom id="94">n</atom><atom id="91">np</atom></impl></formula><formula id="13"><impl><atom id="91">np</atom><atom id="93">np</atom></impl></formula><formula id="14"><impl><atom id="98">np</atom><atom id="89">np</atom></impl></formula></antecedent><formula><atom id="89">np</atom></formula><premisses>
                           <rule name="il"><antecedent><formula id="1"><atom id="109">n</atom></formula><formula id="2"><impl><atom id="109">n</atom><atom id="108">np</atom></impl></formula><formula id="3"><impl><atom id="108">np</atom><impl><atom id="102">np</atom><atom id="106">np</atom></impl></impl></formula><formula id="4"><atom id="103">n</atom></formula><formula id="5"><impl><atom id="103">n</atom><atom id="100">np</atom></impl></formula><formula id="6"><impl><atom id="100">np</atom><atom id="102">np</atom></impl></formula><formula id="7"><impl><atom id="106">np</atom><atom id="116">inf</atom></impl></formula><formula id="8"><impl><atom id="116">inf</atom><atom id="114">inf</atom></impl></formula><formula id="9"><impl><atom id="114">inf</atom><impl><atom id="95">vnw</atom><atom id="112">ssub</atom></impl></impl></formula><formula id="10"><impl><impl><atom id="95">vnw</atom><atom id="112">ssub</atom></impl><impl><atom id="93">np</atom><atom id="98">np</atom></impl></impl></formula><formula id="11"><atom id="94">n</atom></formula><formula id="12"><impl><atom id="94">n</atom><atom id="91">np</atom></impl></formula><formula id="13"><impl><atom id="91">np</atom><atom id="93">np</atom></impl></formula></antecedent><formula><atom id="98">np</atom></formula><premisses>
                              <rule name="ir"><antecedent><formula id="1"><atom id="109">n</atom></formula><formula id="2"><impl><atom id="109">n</atom><atom id="108">np</atom></impl></formula><formula id="3"><impl><atom id="108">np</atom><impl><atom id="102">np</atom><atom id="106">np</atom></impl></impl></formula><formula id="4"><atom id="103">n</atom></formula><formula id="5"><impl><atom id="103">n</atom><atom id="100">np</atom></impl></formula><formula id="6"><impl><atom id="100">np</atom><atom id="102">np</atom></impl></formula><formula id="7"><impl><atom id="106">np</atom><atom id="116">inf</atom></impl></formula><formula id="8"><impl><atom id="116">inf</atom><atom id="114">inf</atom></impl></formula><formula id="9"><impl><atom id="114">inf</atom><impl><atom id="95">vnw</atom><atom id="112">ssub</atom></impl></impl></formula></antecedent><formula><impl><atom id="95">vnw</atom><atom id="112">ssub</atom></impl></formula><premisses>
                                 <rule name="il"><antecedent><formula id="1"><atom id="109">n</atom></formula><formula id="2"><impl><atom id="109">n</atom><atom id="108">np</atom></impl></formula><formula id="3"><impl><atom id="108">np</atom><impl><atom id="102">np</atom><atom id="106">np</atom></impl></impl></formula><formula id="4"><atom id="103">n</atom></formula><formula id="5"><impl><atom id="103">n</atom><atom id="100">np</atom></impl></formula><formula id="6"><impl><atom id="100">np</atom><atom id="102">np</atom></impl></formula><formula id="7"><impl><atom id="106">np</atom><atom id="116">inf</atom></impl></formula><formula id="8"><impl><atom id="116">inf</atom><atom id="114">inf</atom></impl></formula><formula id="9"><impl><atom id="114">inf</atom><impl><atom id="95">vnw</atom><atom id="112">ssub</atom></impl></impl></formula><formula id="10"><atom id="95">vnw</atom></formula></antecedent><formula><atom id="112">ssub</atom></formula><premisses>
                                    <rule name="il"><antecedent><formula id="1"><atom id="109">n</atom></formula><formula id="2"><impl><atom id="109">n</atom><atom id="108">np</atom></impl></formula><formula id="3"><impl><atom id="108">np</atom><impl><atom id="102">np</atom><atom id="106">np</atom></impl></impl></formula><formula id="4"><atom id="103">n</atom></formula><formula id="5"><impl><atom id="103">n</atom><atom id="100">np</atom></impl></formula><formula id="6"><impl><atom id="100">np</atom><atom id="102">np</atom></impl></formula><formula id="7"><impl><atom id="106">np</atom><atom id="116">inf</atom></impl></formula><formula id="8"><impl><atom id="116">inf</atom><atom id="114">inf</atom></impl></formula></antecedent><formula><atom id="114">inf</atom></formula><premisses>
                                       <rule name="il"><antecedent><formula id="1"><atom id="109">n</atom></formula><formula id="2"><impl><atom id="109">n</atom><atom id="108">np</atom></impl></formula><formula id="3"><impl><atom id="108">np</atom><impl><atom id="102">np</atom><atom id="106">np</atom></impl></impl></formula><formula id="4"><atom id="103">n</atom></formula><formula id="5"><impl><atom id="103">n</atom><atom id="100">np</atom></impl></formula><formula id="6"><impl><atom id="100">np</atom><atom id="102">np</atom></impl></formula><formula id="7"><impl><atom id="106">np</atom><atom id="116">inf</atom></impl></formula></antecedent><formula><atom id="116">inf</atom></formula><premisses>
                                          <rule name="il"><antecedent><formula id="1"><atom id="109">n</atom></formula><formula id="2"><impl><atom id="109">n</atom><atom id="108">np</atom></impl></formula><formula id="3"><impl><atom id="108">np</atom><impl><atom id="102">np</atom><atom id="106">np</atom></impl></impl></formula><formula id="4"><atom id="103">n</atom></formula><formula id="5"><impl><atom id="103">n</atom><atom id="100">np</atom></impl></formula><formula id="6"><impl><atom id="100">np</atom><atom id="102">np</atom></impl></formula></antecedent><formula><atom id="106">np</atom></formula><premisses>
                                             <rule name="il"><antecedent><formula id="1"><atom id="109">n</atom></formula><formula id="2"><impl><atom id="109">n</atom><atom id="108">np</atom></impl></formula></antecedent><formula><atom id="108">np</atom></formula><premisses>
                                                <rule name="ax"><antecedent><formula id="1"><atom id="109">n</atom></formula></antecedent><formula><atom id="109">n</atom></formula><premisses></premisses></rule>,
                                                <rule name="ax"><antecedent><formula id="1"><atom id="108">np</atom></formula></antecedent><formula><atom id="108">np</atom></formula><premisses></premisses></rule>
                                                </premisses></rule>,
                                             <rule name="il"><antecedent><formula id="1"><atom id="103">n</atom></formula><formula id="2"><impl><atom id="103">n</atom><atom id="100">np</atom></impl></formula><formula id="3"><impl><atom id="100">np</atom><atom id="102">np</atom></impl></formula><formula id="4"><impl><atom id="102">np</atom><atom id="106">np</atom></impl></formula></antecedent><formula><atom id="106">np</atom></formula><premisses>
                                                <rule name="il"><antecedent><formula id="1"><atom id="103">n</atom></formula><formula id="2"><impl><atom id="103">n</atom><atom id="100">np</atom></impl></formula><formula id="3"><impl><atom id="100">np</atom><atom id="102">np</atom></impl></formula></antecedent><formula><atom id="102">np</atom></formula><premisses>
                                                   <rule name="il"><antecedent><formula id="1"><atom id="103">n</atom></formula><formula id="2"><impl><atom id="103">n</atom><atom id="100">np</atom></impl></formula></antecedent><formula><atom id="100">np</atom></formula><premisses>
                                                      <rule name="ax"><antecedent><formula id="1"><atom id="103">n</atom></formula></antecedent><formula><atom id="103">n</atom></formula><premisses></premisses></rule>,
                                                      <rule name="ax"><antecedent><formula id="1"><atom id="100">np</atom></formula></antecedent><formula><atom id="100">np</atom></formula><premisses></premisses></rule>
                                                      </premisses></rule>,
                                                   <rule name="ax"><antecedent><formula id="1"><atom id="102">np</atom></formula></antecedent><formula><atom id="102">np</atom></formula><premisses></premisses></rule>
                                                   </premisses></rule>,
                                                <rule name="ax"><antecedent><formula id="1"><atom id="106">np</atom></formula></antecedent><formula><atom id="106">np</atom></formula><premisses></premisses></rule>
                                                </premisses></rule>
                                             </premisses></rule>,
                                          <rule name="ax"><antecedent><formula id="1"><atom id="116">inf</atom></formula></antecedent><formula><atom id="116">inf</atom></formula><premisses></premisses></rule>
                                          </premisses></rule>,
                                       <rule name="ax"><antecedent><formula id="1"><atom id="114">inf</atom></formula></antecedent><formula><atom id="114">inf</atom></formula><premisses></premisses></rule>
                                       </premisses></rule>,
                                    <rule name="il"><antecedent><formula id="1"><atom id="95">vnw</atom></formula><formula id="2"><impl><atom id="95">vnw</atom><atom id="112">ssub</atom></impl></formula></antecedent><formula><atom id="112">ssub</atom></formula><premisses>
                                       <rule name="ax"><antecedent><formula id="1"><atom id="95">vnw</atom></formula></antecedent><formula><atom id="95">vnw</atom></formula><premisses></premisses></rule>,
                                       <rule name="ax"><antecedent><formula id="1"><atom id="112">ssub</atom></formula></antecedent><formula><atom id="112">ssub</atom></formula><premisses></premisses></rule>
                                       </premisses></rule>
                                    </premisses></rule>
                                 </premisses></rule>,
                              <rule name="il"><antecedent><formula id="1"><atom id="94">n</atom></formula><formula id="2"><impl><atom id="94">n</atom><atom id="91">np</atom></impl></formula><formula id="3"><impl><atom id="91">np</atom><atom id="93">np</atom></impl></formula><formula id="4"><impl><atom id="93">np</atom><atom id="98">np</atom></impl></formula></antecedent><formula><atom id="98">np</atom></formula><premisses>
                                 <rule name="il"><antecedent><formula id="1"><atom id="94">n</atom></formula><formula id="2"><impl><atom id="94">n</atom><atom id="91">np</atom></impl></formula><formula id="3"><impl><atom id="91">np</atom><atom id="93">np</atom></impl></formula></antecedent><formula><atom id="93">np</atom></formula><premisses>
                                    <rule name="il"><antecedent><formula id="1"><atom id="94">n</atom></formula><formula id="2"><impl><atom id="94">n</atom><atom id="91">np</atom></impl></formula></antecedent><formula><atom id="91">np</atom></formula><premisses>
                                       <rule name="ax"><antecedent><formula id="1"><atom id="94">n</atom></formula></antecedent><formula><atom id="94">n</atom></formula><premisses></premisses></rule>,
                                       <rule name="ax"><antecedent><formula id="1"><atom id="91">np</atom></formula></antecedent><formula><atom id="91">np</atom></formula><premisses></premisses></rule>
                                       </premisses></rule>,
                                    <rule name="ax"><antecedent><formula id="1"><atom id="93">np</atom></formula></antecedent><formula><atom id="93">np</atom></formula><premisses></premisses></rule>
                                    </premisses></rule>,
                                 <rule name="ax"><antecedent><formula id="1"><atom id="98">np</atom></formula></antecedent><formula><atom id="98">np</atom></formula><premisses></premisses></rule>
                                 </premisses></rule>
                              </premisses></rule>,
                           <rule name="ax"><antecedent><formula id="1"><atom id="89">np</atom></formula></antecedent><formula><atom id="89">np</atom></formula><premisses></premisses></rule>
                           </premisses></rule>
                        </premisses></rule>
                     </premisses></rule>,
                  <rule name="il"><antecedent><formula id="1"><atom id="41">np</atom></formula><formula id="2"><impl><atom id="41">np</atom><atom id="45">np</atom></impl></formula></antecedent><formula><atom id="45">np</atom></formula><premisses>
                     <rule name="ax"><antecedent><formula id="1"><atom id="41">np</atom></formula></antecedent><formula><atom id="41">np</atom></formula><premisses></premisses></rule>,
                     <rule name="ax"><antecedent><formula id="1"><atom id="45">np</atom></formula></antecedent><formula><atom id="45">np</atom></formula><premisses></premisses></rule>
                     </premisses></rule>
                  </premisses></rule>,
               <rule name="il"><antecedent><formula id="1"><atom id="40">n</atom></formula><formula id="2"><impl><atom id="40">n</atom><atom id="39">np</atom></impl></formula><formula id="3"><impl><atom id="39">np</atom><atom id="37">smain</atom></impl></formula></antecedent><formula><atom id="37">smain</atom></formula><premisses>
                  <rule name="il"><antecedent><formula id="1"><atom id="40">n</atom></formula><formula id="2"><impl><atom id="40">n</atom><atom id="39">np</atom></impl></formula></antecedent><formula><atom id="39">np</atom></formula><premisses>
                     <rule name="ax"><antecedent><formula id="1"><atom id="40">n</atom></formula></antecedent><formula><atom id="40">n</atom></formula><premisses></premisses></rule>,
                     <rule name="ax"><antecedent><formula id="1"><atom id="39">np</atom></formula></antecedent><formula><atom id="39">np</atom></formula><premisses></premisses></rule>
                     </premisses></rule>,
                  <rule name="ax"><antecedent><formula id="1"><atom id="37">smain</atom></formula></antecedent><formula><atom id="37">smain</atom></formula><premisses></premisses></rule>
                  </premisses></rule>
               </premisses></rule>
            </premisses></rule>,
         <rule name="ax"><antecedent><formula id="1"><atom id="4">smain</atom></formula></antecedent><formula><atom id="4">smain</atom></formula><premisses></premisses></rule>
         </premisses></rule>
      </premisses></rule>
   </premisses></rule>
</proof>
