<proof id="wiki-3824.p.2.s.3_0.xml" date="27052020">
 <string>Ten noorden grenst de provincie aan de provincie Luik en ten westen aan de provincie Namen</string>
 <lexicon>
  <lexicon_item id="1"><word>Ten</word><pos1>prep</pos1><pos2>VZ(versm)</pos2><lemma>te</lemma><formula><impl><dia dep="obj1"><atom id="3">n</atom></dia><box dep="mod"><impl><atom id="19">smain</atom><atom id="2">smain</atom></impl></box></impl></formula></lexicon_item>
  <lexicon_item id="2"><word>noorden</word><pos1>noun</pos1><pos2>N(soort,ev,basis,onz,stan)</pos2><lemma>noorden</lemma><formula><atom id="3">n</atom></formula></lexicon_item>
  <lexicon_item id="3"><word>grenst</word><pos1>verb</pos1><pos2>WW(pv,tgw,met-t)</pos2><lemma>grenzen</lemma><formula><impl><dia dep="pc"><atom id="27">pp</atom></dia><impl><dia dep="su"><atom id="28">np</atom></dia><atom id="6">smain</atom></impl></impl></formula></lexicon_item>
  <lexicon_item id="4"><word>de</word><pos1>det</pos1><pos2>LID(bep,stan,rest)</pos2><lemma>de</lemma><formula><box dep="det"><impl><atom id="9">n</atom><atom id="8">np</atom></impl></box></formula></lexicon_item>
  <lexicon_item id="5"><word>provincie</word><pos1>noun</pos1><pos2>N(soort,ev,basis,zijd,stan)</pos2><lemma>provincie</lemma><formula><atom id="9">n</atom></formula></lexicon_item>
  <lexicon_item id="6"><word>aan</word><pos1>prep</pos1><pos2>VZ(init)</pos2><lemma>aan</lemma><formula><impl><dia dep="obj1"><atom id="16">np</atom></dia><atom id="11">pp</atom></impl></formula></lexicon_item>
  <lexicon_item id="7"><word>de</word><pos1>det</pos1><pos2>LID(bep,stan,rest)</pos2><lemma>de</lemma><formula><box dep="det"><impl><atom id="14">n</atom><atom id="13">np</atom></impl></box></formula></lexicon_item>
  <lexicon_item id="8"><word>provincie</word><pos1>noun</pos1><pos2>N(soort,ev,basis,zijd,stan)</pos2><lemma>provincie</lemma><formula><atom id="14">n</atom></formula></lexicon_item>
  <lexicon_item id="9"><word>Luik</word><pos1>name</pos1><pos2>N(eigen,ev,basis,onz,stan)</pos2><lemma>Luik</lemma><formula><box dep="app"><impl><atom id="13">np</atom><atom id="16">np</atom></impl></box></formula></lexicon_item>
  <lexicon_item id="10"><word>en</word><pos1>vg</pos1><pos2>VG(neven)</pos2><lemma>en</lemma><formula><impl><dia dep="cnj"><impl><impl><dia dep="pc"><atom id="11">pp</atom></dia><impl><dia dep="su"><atom id="20">np</atom></dia><atom id="19">smain</atom></impl></impl><impl><dia dep="su"><atom id="20">np</atom></dia><atom id="2">smain</atom></impl></impl></dia><impl><dia dep="cnj"><impl><impl><dia dep="pc"><atom id="37">pp</atom></dia><impl><dia dep="su"><atom id="25">np</atom></dia><atom id="24">smain</atom></impl></impl><impl><dia dep="su"><atom id="25">np</atom></dia><atom id="34">smain</atom></impl></impl></dia><impl><impl><dia dep="pc"><atom id="27">pp</atom></dia><impl><dia dep="su"><atom id="28">np</atom></dia><atom id="6">smain</atom></impl></impl><impl><dia dep="su"><atom id="8">np</atom></dia><atom id="31">smain</atom></impl></impl></impl></impl></formula></lexicon_item>
  <lexicon_item id="11"><word>ten</word><pos1>prep</pos1><pos2>VZ(versm)</pos2><lemma>te</lemma><formula><impl><dia dep="obj1"><atom id="35">n</atom></dia><box dep="mod"><impl><atom id="24">smain</atom><atom id="34">smain</atom></impl></box></impl></formula></lexicon_item>
  <lexicon_item id="12"><word>westen</word><pos1>noun</pos1><pos2>N(soort,ev,basis,onz,stan)</pos2><lemma>westen</lemma><formula><atom id="35">n</atom></formula></lexicon_item>
  <lexicon_item id="13"><word>aan</word><pos1>prep</pos1><pos2>VZ(init)</pos2><lemma>aan</lemma><formula><impl><dia dep="obj1"><atom id="42">np</atom></dia><atom id="37">pp</atom></impl></formula></lexicon_item>
  <lexicon_item id="14"><word>de</word><pos1>det</pos1><pos2>LID(bep,stan,rest)</pos2><lemma>de</lemma><formula><box dep="det"><impl><atom id="40">n</atom><atom id="39">np</atom></impl></box></formula></lexicon_item>
  <lexicon_item id="15"><word>provincie</word><pos1>noun</pos1><pos2>N(soort,ev,basis,zijd,stan)</pos2><lemma>provincie</lemma><formula><atom id="40">n</atom></formula></lexicon_item>
  <lexicon_item id="16"><word>Namen</word><pos1>name</pos1><pos2>N(eigen,ev,basis,onz,stan)</pos2><lemma>Namen</lemma><formula><box dep="app"><impl><atom id="39">np</atom><atom id="42">np</atom></impl></box></formula></lexicon_item>
 </lexicon>
<rule name="il"><antecedent><formula id="1"><atom id="3">n</atom></formula><formula id="2"><impl><atom id="3">n</atom><impl><atom id="19">smain</atom><atom id="2">smain</atom></impl></impl></formula><formula id="3"><atom id="14">n</atom></formula><formula id="4"><impl><atom id="14">n</atom><atom id="13">np</atom></impl></formula><formula id="5"><impl><atom id="13">np</atom><atom id="16">np</atom></impl></formula><formula id="6"><impl><atom id="16">np</atom><atom id="11">pp</atom></impl></formula><formula id="7"><impl><impl><impl><atom id="11">pp</atom><impl><atom id="20">np</atom><atom id="19">smain</atom></impl></impl><impl><atom id="20">np</atom><atom id="2">smain</atom></impl></impl><impl><impl><impl><atom id="37">pp</atom><impl><atom id="25">np</atom><atom id="24">smain</atom></impl></impl><impl><atom id="25">np</atom><atom id="34">smain</atom></impl></impl><impl><impl><atom id="27">pp</atom><impl><atom id="28">np</atom><atom id="6">smain</atom></impl></impl><impl><atom id="8">np</atom><atom id="31">smain</atom></impl></impl></impl></impl></formula><formula id="8"><atom id="35">n</atom></formula><formula id="9"><impl><atom id="35">n</atom><impl><atom id="24">smain</atom><atom id="34">smain</atom></impl></impl></formula><formula id="10"><atom id="40">n</atom></formula><formula id="11"><impl><atom id="40">n</atom><atom id="39">np</atom></impl></formula><formula id="12"><impl><atom id="39">np</atom><atom id="42">np</atom></impl></formula><formula id="13"><impl><atom id="42">np</atom><atom id="37">pp</atom></impl></formula><formula id="14"><impl><atom id="27">pp</atom><impl><atom id="28">np</atom><atom id="6">smain</atom></impl></impl></formula><formula id="15"><atom id="9">n</atom></formula><formula id="16"><impl><atom id="9">n</atom><atom id="8">np</atom></impl></formula></antecedent><formula><atom id="31">smain</atom></formula><premisses>
   <rule name="ir"><antecedent><formula id="1"><atom id="3">n</atom></formula><formula id="2"><impl><atom id="3">n</atom><impl><atom id="19">smain</atom><atom id="2">smain</atom></impl></impl></formula><formula id="3"><atom id="14">n</atom></formula><formula id="4"><impl><atom id="14">n</atom><atom id="13">np</atom></impl></formula><formula id="5"><impl><atom id="13">np</atom><atom id="16">np</atom></impl></formula><formula id="6"><impl><atom id="16">np</atom><atom id="11">pp</atom></impl></formula></antecedent><formula><impl><impl><atom id="11">pp</atom><impl><atom id="20">np</atom><atom id="19">smain</atom></impl></impl><impl><atom id="20">np</atom><atom id="2">smain</atom></impl></impl></formula><premisses>
      <rule name="ir"><antecedent><formula id="1"><atom id="3">n</atom></formula><formula id="2"><impl><atom id="3">n</atom><impl><atom id="19">smain</atom><atom id="2">smain</atom></impl></impl></formula><formula id="3"><atom id="14">n</atom></formula><formula id="4"><impl><atom id="14">n</atom><atom id="13">np</atom></impl></formula><formula id="5"><impl><atom id="13">np</atom><atom id="16">np</atom></impl></formula><formula id="6"><impl><atom id="16">np</atom><atom id="11">pp</atom></impl></formula><formula id="7"><impl><atom id="11">pp</atom><impl><atom id="20">np</atom><atom id="19">smain</atom></impl></impl></formula></antecedent><formula><impl><atom id="20">np</atom><atom id="2">smain</atom></impl></formula><premisses>
         <rule name="il"><antecedent><formula id="1"><atom id="3">n</atom></formula><formula id="2"><impl><atom id="3">n</atom><impl><atom id="19">smain</atom><atom id="2">smain</atom></impl></impl></formula><formula id="3"><atom id="14">n</atom></formula><formula id="4"><impl><atom id="14">n</atom><atom id="13">np</atom></impl></formula><formula id="5"><impl><atom id="13">np</atom><atom id="16">np</atom></impl></formula><formula id="6"><impl><atom id="16">np</atom><atom id="11">pp</atom></impl></formula><formula id="7"><impl><atom id="11">pp</atom><impl><atom id="20">np</atom><atom id="19">smain</atom></impl></impl></formula><formula id="8"><atom id="20">np</atom></formula></antecedent><formula><atom id="2">smain</atom></formula><premisses>
            <rule name="ax"><antecedent><formula id="1"><atom id="3">n</atom></formula></antecedent><formula><atom id="3">n</atom></formula><premisses></premisses></rule>,
            <rule name="il"><antecedent><formula id="1"><atom id="14">n</atom></formula><formula id="2"><impl><atom id="14">n</atom><atom id="13">np</atom></impl></formula><formula id="3"><impl><atom id="13">np</atom><atom id="16">np</atom></impl></formula><formula id="4"><impl><atom id="16">np</atom><atom id="11">pp</atom></impl></formula><formula id="5"><impl><atom id="11">pp</atom><impl><atom id="20">np</atom><atom id="19">smain</atom></impl></impl></formula><formula id="6"><atom id="20">np</atom></formula><formula id="7"><impl><atom id="19">smain</atom><atom id="2">smain</atom></impl></formula></antecedent><formula><atom id="2">smain</atom></formula><premisses>
               <rule name="il"><antecedent><formula id="1"><atom id="14">n</atom></formula><formula id="2"><impl><atom id="14">n</atom><atom id="13">np</atom></impl></formula><formula id="3"><impl><atom id="13">np</atom><atom id="16">np</atom></impl></formula><formula id="4"><impl><atom id="16">np</atom><atom id="11">pp</atom></impl></formula><formula id="5"><impl><atom id="11">pp</atom><impl><atom id="20">np</atom><atom id="19">smain</atom></impl></impl></formula><formula id="6"><atom id="20">np</atom></formula></antecedent><formula><atom id="19">smain</atom></formula><premisses>
                  <rule name="il"><antecedent><formula id="1"><atom id="14">n</atom></formula><formula id="2"><impl><atom id="14">n</atom><atom id="13">np</atom></impl></formula><formula id="3"><impl><atom id="13">np</atom><atom id="16">np</atom></impl></formula><formula id="4"><impl><atom id="16">np</atom><atom id="11">pp</atom></impl></formula></antecedent><formula><atom id="11">pp</atom></formula><premisses>
                     <rule name="il"><antecedent><formula id="1"><atom id="14">n</atom></formula><formula id="2"><impl><atom id="14">n</atom><atom id="13">np</atom></impl></formula><formula id="3"><impl><atom id="13">np</atom><atom id="16">np</atom></impl></formula></antecedent><formula><atom id="16">np</atom></formula><premisses>
                        <rule name="il"><antecedent><formula id="1"><atom id="14">n</atom></formula><formula id="2"><impl><atom id="14">n</atom><atom id="13">np</atom></impl></formula></antecedent><formula><atom id="13">np</atom></formula><premisses>
                           <rule name="ax"><antecedent><formula id="1"><atom id="14">n</atom></formula></antecedent><formula><atom id="14">n</atom></formula><premisses></premisses></rule>,
                           <rule name="ax"><antecedent><formula id="1"><atom id="13">np</atom></formula></antecedent><formula><atom id="13">np</atom></formula><premisses></premisses></rule>
                           </premisses></rule>,
                        <rule name="ax"><antecedent><formula id="1"><atom id="16">np</atom></formula></antecedent><formula><atom id="16">np</atom></formula><premisses></premisses></rule>
                        </premisses></rule>,
                     <rule name="ax"><antecedent><formula id="1"><atom id="11">pp</atom></formula></antecedent><formula><atom id="11">pp</atom></formula><premisses></premisses></rule>
                     </premisses></rule>,
                  <rule name="il"><antecedent><formula id="1"><atom id="20">np</atom></formula><formula id="2"><impl><atom id="20">np</atom><atom id="19">smain</atom></impl></formula></antecedent><formula><atom id="19">smain</atom></formula><premisses>
                     <rule name="ax"><antecedent><formula id="1"><atom id="20">np</atom></formula></antecedent><formula><atom id="20">np</atom></formula><premisses></premisses></rule>,
                     <rule name="ax"><antecedent><formula id="1"><atom id="19">smain</atom></formula></antecedent><formula><atom id="19">smain</atom></formula><premisses></premisses></rule>
                     </premisses></rule>
                  </premisses></rule>,
               <rule name="ax"><antecedent><formula id="1"><atom id="2">smain</atom></formula></antecedent><formula><atom id="2">smain</atom></formula><premisses></premisses></rule>
               </premisses></rule>
            </premisses></rule>
         </premisses></rule>
      </premisses></rule>,
   <rule name="il"><antecedent><formula id="1"><atom id="35">n</atom></formula><formula id="2"><impl><atom id="35">n</atom><impl><atom id="24">smain</atom><atom id="34">smain</atom></impl></impl></formula><formula id="3"><atom id="40">n</atom></formula><formula id="4"><impl><atom id="40">n</atom><atom id="39">np</atom></impl></formula><formula id="5"><impl><atom id="39">np</atom><atom id="42">np</atom></impl></formula><formula id="6"><impl><atom id="42">np</atom><atom id="37">pp</atom></impl></formula><formula id="7"><impl><impl><impl><atom id="37">pp</atom><impl><atom id="25">np</atom><atom id="24">smain</atom></impl></impl><impl><atom id="25">np</atom><atom id="34">smain</atom></impl></impl><impl><impl><atom id="27">pp</atom><impl><atom id="28">np</atom><atom id="6">smain</atom></impl></impl><impl><atom id="8">np</atom><atom id="31">smain</atom></impl></impl></impl></formula><formula id="8"><impl><atom id="27">pp</atom><impl><atom id="28">np</atom><atom id="6">smain</atom></impl></impl></formula><formula id="9"><atom id="9">n</atom></formula><formula id="10"><impl><atom id="9">n</atom><atom id="8">np</atom></impl></formula></antecedent><formula><atom id="31">smain</atom></formula><premisses>
      <rule name="ir"><antecedent><formula id="1"><atom id="35">n</atom></formula><formula id="2"><impl><atom id="35">n</atom><impl><atom id="24">smain</atom><atom id="34">smain</atom></impl></impl></formula><formula id="3"><atom id="40">n</atom></formula><formula id="4"><impl><atom id="40">n</atom><atom id="39">np</atom></impl></formula><formula id="5"><impl><atom id="39">np</atom><atom id="42">np</atom></impl></formula><formula id="6"><impl><atom id="42">np</atom><atom id="37">pp</atom></impl></formula></antecedent><formula><impl><impl><atom id="37">pp</atom><impl><atom id="25">np</atom><atom id="24">smain</atom></impl></impl><impl><atom id="25">np</atom><atom id="34">smain</atom></impl></impl></formula><premisses>
         <rule name="ir"><antecedent><formula id="1"><atom id="35">n</atom></formula><formula id="2"><impl><atom id="35">n</atom><impl><atom id="24">smain</atom><atom id="34">smain</atom></impl></impl></formula><formula id="3"><atom id="40">n</atom></formula><formula id="4"><impl><atom id="40">n</atom><atom id="39">np</atom></impl></formula><formula id="5"><impl><atom id="39">np</atom><atom id="42">np</atom></impl></formula><formula id="6"><impl><atom id="42">np</atom><atom id="37">pp</atom></impl></formula><formula id="7"><impl><atom id="37">pp</atom><impl><atom id="25">np</atom><atom id="24">smain</atom></impl></impl></formula></antecedent><formula><impl><atom id="25">np</atom><atom id="34">smain</atom></impl></formula><premisses>
            <rule name="il"><antecedent><formula id="1"><atom id="35">n</atom></formula><formula id="2"><impl><atom id="35">n</atom><impl><atom id="24">smain</atom><atom id="34">smain</atom></impl></impl></formula><formula id="3"><atom id="40">n</atom></formula><formula id="4"><impl><atom id="40">n</atom><atom id="39">np</atom></impl></formula><formula id="5"><impl><atom id="39">np</atom><atom id="42">np</atom></impl></formula><formula id="6"><impl><atom id="42">np</atom><atom id="37">pp</atom></impl></formula><formula id="7"><impl><atom id="37">pp</atom><impl><atom id="25">np</atom><atom id="24">smain</atom></impl></impl></formula><formula id="8"><atom id="25">np</atom></formula></antecedent><formula><atom id="34">smain</atom></formula><premisses>
               <rule name="ax"><antecedent><formula id="1"><atom id="35">n</atom></formula></antecedent><formula><atom id="35">n</atom></formula><premisses></premisses></rule>,
               <rule name="il"><antecedent><formula id="1"><atom id="40">n</atom></formula><formula id="2"><impl><atom id="40">n</atom><atom id="39">np</atom></impl></formula><formula id="3"><impl><atom id="39">np</atom><atom id="42">np</atom></impl></formula><formula id="4"><impl><atom id="42">np</atom><atom id="37">pp</atom></impl></formula><formula id="5"><impl><atom id="37">pp</atom><impl><atom id="25">np</atom><atom id="24">smain</atom></impl></impl></formula><formula id="6"><atom id="25">np</atom></formula><formula id="7"><impl><atom id="24">smain</atom><atom id="34">smain</atom></impl></formula></antecedent><formula><atom id="34">smain</atom></formula><premisses>
                  <rule name="il"><antecedent><formula id="1"><atom id="40">n</atom></formula><formula id="2"><impl><atom id="40">n</atom><atom id="39">np</atom></impl></formula><formula id="3"><impl><atom id="39">np</atom><atom id="42">np</atom></impl></formula><formula id="4"><impl><atom id="42">np</atom><atom id="37">pp</atom></impl></formula><formula id="5"><impl><atom id="37">pp</atom><impl><atom id="25">np</atom><atom id="24">smain</atom></impl></impl></formula><formula id="6"><atom id="25">np</atom></formula></antecedent><formula><atom id="24">smain</atom></formula><premisses>
                     <rule name="il"><antecedent><formula id="1"><atom id="40">n</atom></formula><formula id="2"><impl><atom id="40">n</atom><atom id="39">np</atom></impl></formula><formula id="3"><impl><atom id="39">np</atom><atom id="42">np</atom></impl></formula><formula id="4"><impl><atom id="42">np</atom><atom id="37">pp</atom></impl></formula></antecedent><formula><atom id="37">pp</atom></formula><premisses>
                        <rule name="il"><antecedent><formula id="1"><atom id="40">n</atom></formula><formula id="2"><impl><atom id="40">n</atom><atom id="39">np</atom></impl></formula><formula id="3"><impl><atom id="39">np</atom><atom id="42">np</atom></impl></formula></antecedent><formula><atom id="42">np</atom></formula><premisses>
                           <rule name="il"><antecedent><formula id="1"><atom id="40">n</atom></formula><formula id="2"><impl><atom id="40">n</atom><atom id="39">np</atom></impl></formula></antecedent><formula><atom id="39">np</atom></formula><premisses>
                              <rule name="ax"><antecedent><formula id="1"><atom id="40">n</atom></formula></antecedent><formula><atom id="40">n</atom></formula><premisses></premisses></rule>,
                              <rule name="ax"><antecedent><formula id="1"><atom id="39">np</atom></formula></antecedent><formula><atom id="39">np</atom></formula><premisses></premisses></rule>
                              </premisses></rule>,
                           <rule name="ax"><antecedent><formula id="1"><atom id="42">np</atom></formula></antecedent><formula><atom id="42">np</atom></formula><premisses></premisses></rule>
                           </premisses></rule>,
                        <rule name="ax"><antecedent><formula id="1"><atom id="37">pp</atom></formula></antecedent><formula><atom id="37">pp</atom></formula><premisses></premisses></rule>
                        </premisses></rule>,
                     <rule name="il"><antecedent><formula id="1"><atom id="25">np</atom></formula><formula id="2"><impl><atom id="25">np</atom><atom id="24">smain</atom></impl></formula></antecedent><formula><atom id="24">smain</atom></formula><premisses>
                        <rule name="ax"><antecedent><formula id="1"><atom id="25">np</atom></formula></antecedent><formula><atom id="25">np</atom></formula><premisses></premisses></rule>,
                        <rule name="ax"><antecedent><formula id="1"><atom id="24">smain</atom></formula></antecedent><formula><atom id="24">smain</atom></formula><premisses></premisses></rule>
                        </premisses></rule>
                     </premisses></rule>,
                  <rule name="ax"><antecedent><formula id="1"><atom id="34">smain</atom></formula></antecedent><formula><atom id="34">smain</atom></formula><premisses></premisses></rule>
                  </premisses></rule>
               </premisses></rule>
            </premisses></rule>
         </premisses></rule>,
      <rule name="il"><antecedent><formula id="1"><impl><atom id="27">pp</atom><impl><atom id="28">np</atom><atom id="6">smain</atom></impl></impl></formula><formula id="2"><impl><impl><atom id="27">pp</atom><impl><atom id="28">np</atom><atom id="6">smain</atom></impl></impl><impl><atom id="8">np</atom><atom id="31">smain</atom></impl></impl></formula><formula id="3"><atom id="9">n</atom></formula><formula id="4"><impl><atom id="9">n</atom><atom id="8">np</atom></impl></formula></antecedent><formula><atom id="31">smain</atom></formula><premisses>
         <rule name="ir"><antecedent><formula id="1"><impl><atom id="27">pp</atom><impl><atom id="28">np</atom><atom id="6">smain</atom></impl></impl></formula></antecedent><formula><impl><atom id="27">pp</atom><impl><atom id="28">np</atom><atom id="6">smain</atom></impl></impl></formula><premisses>
            <rule name="ir"><antecedent><formula id="1"><atom id="27">pp</atom></formula><formula id="2"><impl><atom id="27">pp</atom><impl><atom id="28">np</atom><atom id="6">smain</atom></impl></impl></formula></antecedent><formula><impl><atom id="28">np</atom><atom id="6">smain</atom></impl></formula><premisses>
               <rule name="il"><antecedent><formula id="1"><atom id="27">pp</atom></formula><formula id="2"><impl><atom id="27">pp</atom><impl><atom id="28">np</atom><atom id="6">smain</atom></impl></impl></formula><formula id="3"><atom id="28">np</atom></formula></antecedent><formula><atom id="6">smain</atom></formula><premisses>
                  <rule name="ax"><antecedent><formula id="1"><atom id="27">pp</atom></formula></antecedent><formula><atom id="27">pp</atom></formula><premisses></premisses></rule>,
                  <rule name="il"><antecedent><formula id="1"><atom id="28">np</atom></formula><formula id="2"><impl><atom id="28">np</atom><atom id="6">smain</atom></impl></formula></antecedent><formula><atom id="6">smain</atom></formula><premisses>
                     <rule name="ax"><antecedent><formula id="1"><atom id="28">np</atom></formula></antecedent><formula><atom id="28">np</atom></formula><premisses></premisses></rule>,
                     <rule name="ax"><antecedent><formula id="1"><atom id="6">smain</atom></formula></antecedent><formula><atom id="6">smain</atom></formula><premisses></premisses></rule>
                     </premisses></rule>
                  </premisses></rule>
               </premisses></rule>
            </premisses></rule>,
         <rule name="il"><antecedent><formula id="1"><atom id="9">n</atom></formula><formula id="2"><impl><atom id="9">n</atom><atom id="8">np</atom></impl></formula><formula id="3"><impl><atom id="8">np</atom><atom id="31">smain</atom></impl></formula></antecedent><formula><atom id="31">smain</atom></formula><premisses>
            <rule name="il"><antecedent><formula id="1"><atom id="9">n</atom></formula><formula id="2"><impl><atom id="9">n</atom><atom id="8">np</atom></impl></formula></antecedent><formula><atom id="8">np</atom></formula><premisses>
               <rule name="ax"><antecedent><formula id="1"><atom id="9">n</atom></formula></antecedent><formula><atom id="9">n</atom></formula><premisses></premisses></rule>,
               <rule name="ax"><antecedent><formula id="1"><atom id="8">np</atom></formula></antecedent><formula><atom id="8">np</atom></formula><premisses></premisses></rule>
               </premisses></rule>,
            <rule name="ax"><antecedent><formula id="1"><atom id="31">smain</atom></formula></antecedent><formula><atom id="31">smain</atom></formula><premisses></premisses></rule>
            </premisses></rule>
         </premisses></rule>
      </premisses></rule>
   </premisses></rule>
</proof>
