<proof id="wiki-866.p.45.s.26.xml_2" date="31102019">
 <string>finale tegen Amélie Mauresmo</string>
 <lexicon>
  <lexicon_item id="1"><word>finale</word><pos1>noun</pos1><pos2>N(soort,ev,basis,zijd,stan)</pos2><lemma>finale</lemma><formula><atom id = "0">np</atom></formula></lexicon_item>
  <lexicon_item id="2"><word>tegen</word><pos1>prep</pos1><pos2>VZ(init)</pos2><lemma>tegen</lemma><formula><impl><atom id = "4">spec</atom><impl><atom id = "0">np</atom><atom id = "3">np</atom></impl></impl></formula></lexicon_item>
  <lexicon_item id="3"><word>Amélie Mauresmo</word><pos1>mwp</pos1><pos2>mwp</pos2><lemma>Amélie Mauresmo</lemma><formula><atom id = "4">spec</atom></formula></lexicon_item>
 </lexicon>
<rule name="il"><antecedent><formula id="1"><atom id = "4">spec</atom></formula><formula id="2"><impl><atom id = "4">spec</atom><impl><atom id = "0">np</atom><atom id = "3">np</atom></impl></impl></formula><formula id="3"><atom id = "0">np</atom></formula></antecedent><formula><atom id = "3">np</atom></formula><premisses>
   <rule name="ax"><antecedent><formula id="1"><atom id = "4">spec</atom></formula></antecedent><formula><atom id = "4">spec</atom></formula><premisses></premisses></rule>,
   <rule name="il"><antecedent><formula id="1"><atom id = "0">np</atom></formula><formula id="2"><impl><atom id = "0">np</atom><atom id = "3">np</atom></impl></formula></antecedent><formula><atom id = "3">np</atom></formula><premisses>
      <rule name="ax"><antecedent><formula id="1"><atom id = "0">np</atom></formula></antecedent><formula><atom id = "0">np</atom></formula><premisses></premisses></rule>,
      <rule name="ax"><antecedent><formula id="1"><atom id = "3">np</atom></formula></antecedent><formula><atom id = "3">np</atom></formula><premisses></premisses></rule>
      </premisses></rule>
   </premisses></rule>
</proof>
