<proof id="wiki-6983.p.17.s.2.xml_1" date="31102019">
 <string>tevens in het VB-partijblad van december 1992</string>
 <lexicon>
  <lexicon_item id="1"><word>tevens</word><pos1>adv</pos1><pos2>BW()</pos2><lemma>tevens</lemma><formula><impl><atom id = "3">pp</atom><atom id = "1">pp</atom></impl></formula></lexicon_item>
  <lexicon_item id="2"><word>in</word><pos1>prep</pos1><pos2>VZ(init)</pos2><lemma>in</lemma><formula><impl><atom id = "9">np</atom><atom id = "3">pp</atom></impl></formula></lexicon_item>
  <lexicon_item id="3"><word>het</word><pos1>det</pos1><pos2>LID(bep,stan,evon)</pos2><lemma>het</lemma><formula><impl><atom id = "6">n</atom><atom id = "5">np</atom></impl></formula></lexicon_item>
  <lexicon_item id="4"><word>VB-partijblad</word><pos1>name</pos1><pos2>N(soort,ev,basis,onz,stan)</pos2><lemma>VB-partijblad</lemma><formula><atom id = "6">n</atom></formula></lexicon_item>
  <lexicon_item id="5"><word>van</word><pos1>prep</pos1><pos2>VZ(init)</pos2><lemma>van</lemma><formula><impl><atom id = "12">np</atom><impl><atom id = "5">np</atom><atom id = "9">np</atom></impl></impl></formula></lexicon_item>
  <lexicon_item id="6"><word>december</word><pos1>noun</pos1><pos2>N(eigen,ev,basis,zijd,stan)</pos2><lemma>december</lemma><formula><atom id = "10">np</atom></formula></lexicon_item>
  <lexicon_item id="7"><word>1992</word><pos1>noun</pos1><pos2>TW(hoofd,vrij)</pos2><lemma>1992</lemma><formula><impl><atom id = "10">np</atom><atom id = "12">np</atom></impl></formula></lexicon_item>
 </lexicon>
<rule name="il"><antecedent><formula id="1"><atom id = "10">np</atom></formula><formula id="2"><impl><atom id = "10">np</atom><atom id = "12">np</atom></impl></formula><formula id="3"><impl><atom id = "12">np</atom><impl><atom id = "5">np</atom><atom id = "9">np</atom></impl></impl></formula><formula id="4"><atom id = "6">n</atom></formula><formula id="5"><impl><atom id = "6">n</atom><atom id = "5">np</atom></impl></formula><formula id="6"><impl><atom id = "9">np</atom><atom id = "3">pp</atom></impl></formula><formula id="7"><impl><atom id = "3">pp</atom><atom id = "1">pp</atom></impl></formula></antecedent><formula><atom id = "1">pp</atom></formula><premisses>
   <rule name="il"><antecedent><formula id="1"><atom id = "10">np</atom></formula><formula id="2"><impl><atom id = "10">np</atom><atom id = "12">np</atom></impl></formula><formula id="3"><impl><atom id = "12">np</atom><impl><atom id = "5">np</atom><atom id = "9">np</atom></impl></impl></formula><formula id="4"><atom id = "6">n</atom></formula><formula id="5"><impl><atom id = "6">n</atom><atom id = "5">np</atom></impl></formula><formula id="6"><impl><atom id = "9">np</atom><atom id = "3">pp</atom></impl></formula></antecedent><formula><atom id = "3">pp</atom></formula><premisses>
      <rule name="il"><antecedent><formula id="1"><atom id = "10">np</atom></formula><formula id="2"><impl><atom id = "10">np</atom><atom id = "12">np</atom></impl></formula><formula id="3"><impl><atom id = "12">np</atom><impl><atom id = "5">np</atom><atom id = "9">np</atom></impl></impl></formula><formula id="4"><atom id = "6">n</atom></formula><formula id="5"><impl><atom id = "6">n</atom><atom id = "5">np</atom></impl></formula></antecedent><formula><atom id = "9">np</atom></formula><premisses>
         <rule name="il"><antecedent><formula id="1"><atom id = "10">np</atom></formula><formula id="2"><impl><atom id = "10">np</atom><atom id = "12">np</atom></impl></formula></antecedent><formula><atom id = "12">np</atom></formula><premisses>
            <rule name="ax"><antecedent><formula id="1"><atom id = "10">np</atom></formula></antecedent><formula><atom id = "10">np</atom></formula><premisses></premisses></rule>,
            <rule name="ax"><antecedent><formula id="1"><atom id = "12">np</atom></formula></antecedent><formula><atom id = "12">np</atom></formula><premisses></premisses></rule>
            </premisses></rule>,
         <rule name="il"><antecedent><formula id="1"><atom id = "6">n</atom></formula><formula id="2"><impl><atom id = "6">n</atom><atom id = "5">np</atom></impl></formula><formula id="3"><impl><atom id = "5">np</atom><atom id = "9">np</atom></impl></formula></antecedent><formula><atom id = "9">np</atom></formula><premisses>
            <rule name="il"><antecedent><formula id="1"><atom id = "6">n</atom></formula><formula id="2"><impl><atom id = "6">n</atom><atom id = "5">np</atom></impl></formula></antecedent><formula><atom id = "5">np</atom></formula><premisses>
               <rule name="ax"><antecedent><formula id="1"><atom id = "6">n</atom></formula></antecedent><formula><atom id = "6">n</atom></formula><premisses></premisses></rule>,
               <rule name="ax"><antecedent><formula id="1"><atom id = "5">np</atom></formula></antecedent><formula><atom id = "5">np</atom></formula><premisses></premisses></rule>
               </premisses></rule>,
            <rule name="ax"><antecedent><formula id="1"><atom id = "9">np</atom></formula></antecedent><formula><atom id = "9">np</atom></formula><premisses></premisses></rule>
            </premisses></rule>
         </premisses></rule>,
      <rule name="ax"><antecedent><formula id="1"><atom id = "3">pp</atom></formula></antecedent><formula><atom id = "3">pp</atom></formula><premisses></premisses></rule>
      </premisses></rule>,
   <rule name="ax"><antecedent><formula id="1"><atom id = "1">pp</atom></formula></antecedent><formula><atom id = "1">pp</atom></formula><premisses></premisses></rule>
   </premisses></rule>
</proof>
