<proof id="dpc-fsz-000541-nl-sen.p.10.s.1_1.xml" date="27052020">
 <string>vaste en uitneembare tandprothesen en prothesen die de mondholte dichten</string>
 <lexicon>
  <lexicon_item id="1"><word>vaste</word><pos1>adj</pos1><pos2>ADJ(prenom,basis,met-e,stan)</pos2><lemma>vast</lemma><formula><box dep="mod"><impl><atom id="2">np</atom><atom id="1">np</atom></impl></box></formula></lexicon_item>
  <lexicon_item id="2"><word>en</word><pos1>vg</pos1><pos2>VG(neven)</pos2><lemma>en</lemma><formula><impl><dia dep="cnj"><box dep="mod"><impl><atom id="2">np</atom><atom id="1">np</atom></impl></box></dia><impl><dia dep="cnj"><box dep="mod"><impl><atom id="4">np</atom><atom id="9">np</atom></impl></box></dia><box dep="mod"><impl><atom id="10">np</atom><atom id="7">np</atom></impl></box></impl></impl></formula></lexicon_item>
  <lexicon_item id="3"><word>uitneembare</word><pos1>adj</pos1><pos2>ADJ(prenom,basis,met-e,stan)</pos2><lemma>uitneembaar</lemma><formula><box dep="mod"><impl><atom id="4">np</atom><atom id="9">np</atom></impl></box></formula></lexicon_item>
  <lexicon_item id="4"><word>tandprothesen</word><pos1>noun</pos1><pos2>N(soort,mv,basis)</pos2><lemma>tandprothese</lemma><formula><atom id="10">np</atom></formula></lexicon_item>
  <lexicon_item id="5"><word>en</word><pos1>vg</pos1><pos2>VG(neven)</pos2><lemma>en</lemma><formula><impl><dia dep="cnj"><atom id="7">np</atom></dia><impl><dia dep="cnj"><atom id="18">np</atom></dia><atom id="13">np</atom></impl></impl></formula></lexicon_item>
  <lexicon_item id="6"><word>prothesen</word><pos1>noun</pos1><pos2>N(soort,mv,basis)</pos2><lemma>prothese</lemma><formula><atom id="14">np</atom></formula></lexicon_item>
  <lexicon_item id="7"><word>die</word><pos1>pron</pos1><pos2>VNW(betr,pron,stan,vol,persoon,getal)</pos2><lemma>die</lemma><formula><impl><dia dep="rhd_body"><impl><dia dep="su"><atom id="15">vnw</atom></dia><atom id="24">ssub</atom></impl></dia><box dep="mod"><impl><atom id="14">np</atom><atom id="18">np</atom></impl></box></impl></formula></lexicon_item>
  <lexicon_item id="8"><word>de</word><pos1>det</pos1><pos2>LID(bep,stan,rest)</pos2><lemma>de</lemma><formula><box dep="det"><impl><atom id="21">n</atom><atom id="20">np</atom></impl></box></formula></lexicon_item>
  <lexicon_item id="9"><word>mondholte</word><pos1>noun</pos1><pos2>N(soort,ev,basis,zijd,stan)</pos2><lemma>mondholte</lemma><formula><atom id="21">n</atom></formula></lexicon_item>
  <lexicon_item id="10"><word>dichten</word><pos1>verb</pos1><pos2>WW(pv,tgw,mv)</pos2><lemma>dichten</lemma><formula><impl><dia dep="obj1"><atom id="20">np</atom></dia><impl><dia dep="su"><atom id="15">vnw</atom></dia><atom id="24">ssub</atom></impl></impl></formula></lexicon_item>
 </lexicon>
<rule name="ie"><antecedent><formula id="1"><atom id="14">np</atom></formula><formula id="2"><atom id="21">n</atom></formula><formula id="3"><impl><atom id="21">n</atom><atom id="20">np</atom></impl></formula><formula id="4"><impl><atom id="20">np</atom><impl><atom id="15">vnw</atom><atom id="24">ssub</atom></impl></impl></formula><formula id="5"><impl><impl><atom id="15">vnw</atom><atom id="24">ssub</atom></impl><impl><atom id="14">np</atom><atom id="18">np</atom></impl></impl></formula><formula id="6"><atom id="10">np</atom></formula><formula id="7"><impl><atom id="4">np</atom><atom id="9">np</atom></impl></formula><formula id="8"><impl><atom id="2">np</atom><atom id="1">np</atom></impl></formula><formula id="9"><impl><impl><atom id="2">np</atom><atom id="1">np</atom></impl><impl><impl><atom id="4">np</atom><atom id="9">np</atom></impl><impl><atom id="10">np</atom><atom id="7">np</atom></impl></impl></impl></formula><formula id="10"><impl><atom id="7">np</atom><impl><atom id="18">np</atom><atom id="13">np</atom></impl></impl></formula></antecedent><formula><atom id="13">np</atom></formula><premisses>
   <rule name="ie"><antecedent><formula id="1"><atom id="14">np</atom></formula><formula id="2"><atom id="21">n</atom></formula><formula id="3"><impl><atom id="21">n</atom><atom id="20">np</atom></impl></formula><formula id="4"><impl><atom id="20">np</atom><impl><atom id="15">vnw</atom><atom id="24">ssub</atom></impl></impl></formula><formula id="5"><impl><impl><atom id="15">vnw</atom><atom id="24">ssub</atom></impl><impl><atom id="14">np</atom><atom id="18">np</atom></impl></impl></formula></antecedent><formula><atom id="18">np</atom></formula><premisses>
      <rule name="ax"><antecedent><formula id="1"><atom id="14">np</atom></formula></antecedent><formula><atom id="14">np</atom></formula><premisses></premisses></rule>,
      <rule name="ie"><antecedent><formula id="1"><atom id="21">n</atom></formula><formula id="2"><impl><atom id="21">n</atom><atom id="20">np</atom></impl></formula><formula id="3"><impl><atom id="20">np</atom><impl><atom id="15">vnw</atom><atom id="24">ssub</atom></impl></impl></formula><formula id="4"><impl><impl><atom id="15">vnw</atom><atom id="24">ssub</atom></impl><impl><atom id="14">np</atom><atom id="18">np</atom></impl></impl></formula></antecedent><formula><impl><atom id="14">np</atom><atom id="18">np</atom></impl></formula><premisses>
         <rule name="ii(3)"><antecedent><formula id="1"><atom id="21">n</atom></formula><formula id="2"><impl><atom id="21">n</atom><atom id="20">np</atom></impl></formula><formula id="3"><impl><atom id="20">np</atom><impl><atom id="15">vnw</atom><atom id="24">ssub</atom></impl></impl></formula></antecedent><formula><impl><atom id="15">vnw</atom><atom id="24">ssub</atom></impl></formula><premisses>
            <rule name="ie"><antecedent><formula id="1"><atom id="15">vnw</atom></formula><formula id="2"><atom id="21">n</atom></formula><formula id="3"><impl><atom id="21">n</atom><atom id="20">np</atom></impl></formula><formula id="4"><impl><atom id="20">np</atom><impl><atom id="15">vnw</atom><atom id="24">ssub</atom></impl></impl></formula></antecedent><formula><atom id="24">ssub</atom></formula><premisses>
               <rule name="hyp(3)"><antecedent><formula id="1"><atom id="15">vnw</atom></formula></antecedent><formula><atom id="15">vnw</atom></formula><premisses></premisses></rule>,
               <rule name="ie"><antecedent><formula id="1"><atom id="21">n</atom></formula><formula id="2"><impl><atom id="21">n</atom><atom id="20">np</atom></impl></formula><formula id="3"><impl><atom id="20">np</atom><impl><atom id="15">vnw</atom><atom id="24">ssub</atom></impl></impl></formula></antecedent><formula><impl><atom id="15">vnw</atom><atom id="24">ssub</atom></impl></formula><premisses>
                  <rule name="ie"><antecedent><formula id="1"><atom id="21">n</atom></formula><formula id="2"><impl><atom id="21">n</atom><atom id="20">np</atom></impl></formula></antecedent><formula><atom id="20">np</atom></formula><premisses>
                     <rule name="ax"><antecedent><formula id="1"><atom id="21">n</atom></formula></antecedent><formula><atom id="21">n</atom></formula><premisses></premisses></rule>,
                     <rule name="ax"><antecedent><formula id="1"><impl><atom id="21">n</atom><atom id="20">np</atom></impl></formula></antecedent><formula><impl><atom id="21">n</atom><atom id="20">np</atom></impl></formula><premisses></premisses></rule>
                     </premisses></rule>,
                  <rule name="ax"><antecedent><formula id="1"><impl><atom id="20">np</atom><impl><atom id="15">vnw</atom><atom id="24">ssub</atom></impl></impl></formula></antecedent><formula><impl><atom id="20">np</atom><impl><atom id="15">vnw</atom><atom id="24">ssub</atom></impl></impl></formula><premisses></premisses></rule>
                  </premisses></rule>
               </premisses></rule>
            </premisses></rule>,
         <rule name="ax"><antecedent><formula id="1"><impl><impl><atom id="15">vnw</atom><atom id="24">ssub</atom></impl><impl><atom id="14">np</atom><atom id="18">np</atom></impl></impl></formula></antecedent><formula><impl><impl><atom id="15">vnw</atom><atom id="24">ssub</atom></impl><impl><atom id="14">np</atom><atom id="18">np</atom></impl></impl></formula><premisses></premisses></rule>
         </premisses></rule>
      </premisses></rule>,
   <rule name="ie"><antecedent><formula id="1"><atom id="10">np</atom></formula><formula id="2"><impl><atom id="4">np</atom><atom id="9">np</atom></impl></formula><formula id="3"><impl><atom id="2">np</atom><atom id="1">np</atom></impl></formula><formula id="4"><impl><impl><atom id="2">np</atom><atom id="1">np</atom></impl><impl><impl><atom id="4">np</atom><atom id="9">np</atom></impl><impl><atom id="10">np</atom><atom id="7">np</atom></impl></impl></impl></formula><formula id="5"><impl><atom id="7">np</atom><impl><atom id="18">np</atom><atom id="13">np</atom></impl></impl></formula></antecedent><formula><impl><atom id="18">np</atom><atom id="13">np</atom></impl></formula><premisses>
      <rule name="ie"><antecedent><formula id="1"><atom id="10">np</atom></formula><formula id="2"><impl><atom id="4">np</atom><atom id="9">np</atom></impl></formula><formula id="3"><impl><atom id="2">np</atom><atom id="1">np</atom></impl></formula><formula id="4"><impl><impl><atom id="2">np</atom><atom id="1">np</atom></impl><impl><impl><atom id="4">np</atom><atom id="9">np</atom></impl><impl><atom id="10">np</atom><atom id="7">np</atom></impl></impl></impl></formula></antecedent><formula><atom id="7">np</atom></formula><premisses>
         <rule name="ax"><antecedent><formula id="1"><atom id="10">np</atom></formula></antecedent><formula><atom id="10">np</atom></formula><premisses></premisses></rule>,
         <rule name="ie"><antecedent><formula id="1"><impl><atom id="4">np</atom><atom id="9">np</atom></impl></formula><formula id="2"><impl><atom id="2">np</atom><atom id="1">np</atom></impl></formula><formula id="3"><impl><impl><atom id="2">np</atom><atom id="1">np</atom></impl><impl><impl><atom id="4">np</atom><atom id="9">np</atom></impl><impl><atom id="10">np</atom><atom id="7">np</atom></impl></impl></impl></formula></antecedent><formula><impl><atom id="10">np</atom><atom id="7">np</atom></impl></formula><premisses>
            <rule name="ii(2)"><antecedent><formula id="1"><impl><atom id="4">np</atom><atom id="9">np</atom></impl></formula></antecedent><formula><impl><atom id="4">np</atom><atom id="9">np</atom></impl></formula><premisses>
               <rule name="ie"><antecedent><formula id="1"><atom id="4">np</atom></formula><formula id="2"><impl><atom id="4">np</atom><atom id="9">np</atom></impl></formula></antecedent><formula><atom id="9">np</atom></formula><premisses>
                  <rule name="hyp(2)"><antecedent><formula id="1"><atom id="4">np</atom></formula></antecedent><formula><atom id="4">np</atom></formula><premisses></premisses></rule>,
                  <rule name="ax"><antecedent><formula id="1"><impl><atom id="4">np</atom><atom id="9">np</atom></impl></formula></antecedent><formula><impl><atom id="4">np</atom><atom id="9">np</atom></impl></formula><premisses></premisses></rule>
                  </premisses></rule>
               </premisses></rule>,
            <rule name="ie"><antecedent><formula id="1"><impl><atom id="2">np</atom><atom id="1">np</atom></impl></formula><formula id="2"><impl><impl><atom id="2">np</atom><atom id="1">np</atom></impl><impl><impl><atom id="4">np</atom><atom id="9">np</atom></impl><impl><atom id="10">np</atom><atom id="7">np</atom></impl></impl></impl></formula></antecedent><formula><impl><impl><atom id="4">np</atom><atom id="9">np</atom></impl><impl><atom id="10">np</atom><atom id="7">np</atom></impl></impl></formula><premisses>
               <rule name="ii(1)"><antecedent><formula id="1"><impl><atom id="2">np</atom><atom id="1">np</atom></impl></formula></antecedent><formula><impl><atom id="2">np</atom><atom id="1">np</atom></impl></formula><premisses>
                  <rule name="ie"><antecedent><formula id="1"><atom id="2">np</atom></formula><formula id="2"><impl><atom id="2">np</atom><atom id="1">np</atom></impl></formula></antecedent><formula><atom id="1">np</atom></formula><premisses>
                     <rule name="hyp(1)"><antecedent><formula id="1"><atom id="2">np</atom></formula></antecedent><formula><atom id="2">np</atom></formula><premisses></premisses></rule>,
                     <rule name="ax"><antecedent><formula id="1"><impl><atom id="2">np</atom><atom id="1">np</atom></impl></formula></antecedent><formula><impl><atom id="2">np</atom><atom id="1">np</atom></impl></formula><premisses></premisses></rule>
                     </premisses></rule>
                  </premisses></rule>,
               <rule name="ax"><antecedent><formula id="1"><impl><impl><atom id="2">np</atom><atom id="1">np</atom></impl><impl><impl><atom id="4">np</atom><atom id="9">np</atom></impl><impl><atom id="10">np</atom><atom id="7">np</atom></impl></impl></impl></formula></antecedent><formula><impl><impl><atom id="2">np</atom><atom id="1">np</atom></impl><impl><impl><atom id="4">np</atom><atom id="9">np</atom></impl><impl><atom id="10">np</atom><atom id="7">np</atom></impl></impl></impl></formula><premisses></premisses></rule>
               </premisses></rule>
            </premisses></rule>
         </premisses></rule>,
      <rule name="ax"><antecedent><formula id="1"><impl><atom id="7">np</atom><impl><atom id="18">np</atom><atom id="13">np</atom></impl></impl></formula></antecedent><formula><impl><atom id="7">np</atom><impl><atom id="18">np</atom><atom id="13">np</atom></impl></impl></formula><premisses></premisses></rule>
      </premisses></rule>
   </premisses></rule>
</proof>
